{
  "music": "Music: ",
  "missingEntries": "{{name}}",
  "battleKantoChampion": "B2W2 Kanto Champion Battle",
  "battleJohtoChampion": "B2W2 Johto Champion Battle",
  "battleHoennChampionG5": "B2W2 Hoenn Champion Battle",
  "battleHoennChampionG6": "ORAS Hoenn Champion Battle",
  "battleSinnohChampion": "B2W2 Sinnoh Champion Battle",
  "battleChampionAlder": "BW Unova Champion Battle",
  "battleChampionIris": "B2W2 Unova Champion Battle",
  "battleKalosChampion": "XY Kalos Champion Battle",
  "battleChampionKukui": "SM Alola Champion Battle",
  "battleAlolaChampion": "USUM Alola Champion Battle",
  "battleGalarChampion": "SWSH Galar Champion Battle",
  "battleMustard": "SWSH Mustard Battle",
  "battleChampionGeeta": "SV Champion Geeta Battle",
  "battleChampionNemona": "SV Champion Nemona Battle",
  "battleChampionKieran": "SV Champion Kieran Battle",
  "battleHoennElite": "ORAS Elite Four Battle",
  "battleUnovaElite": "BW Elite Four Battle",
  "battleKalosElite": "XY Elite Four Battle",
  "battleAlolaElite": "SM Elite Four Battle",
  "battleGalarElite": "SWSH League Tournament Battle",
  "battlePaldeaElite": "SV Elite Four Battle",
  "battleBbElite": "SV BB League Elite Four Battle",
  "battleFinalEncounter": "PMD RTDX Rayquaza’s Domain",
  "battleFinal": "BW Ghetsis Battle",
  "battleKantoGym": "B2W2 Kanto Gym Battle",
  "battleJohtoGym": "B2W2 Johto Gym Battle",
  "battleHoennGym": "B2W2 Hoenn Gym Battle",
  "battleSinnohGym": "B2W2 Sinnoh Gym Battle",
  "battleUnovaGym": "BW Unova Gym Battle",
  "battleKalosGym": "XY Kalos Gym Battle",
  "battleGalarGym": "SWSH Galar Gym Battle",
  "battlePaldeaGym": "SV Paldea Gym Battle",
  "battleLegendaryKanto": "XY Kanto Legendary Battle",
  "battleLegendaryRaikou": "HGSS Raikou Battle",
  "battleLegendaryEntei": "HGSS Entei Battle",
  "battleLegendarySuicune": "HGSS Suicune Battle",
  "battleLegendaryLugia": "HGSS Lugia Battle",
  "battleLegendaryHoOh": "HGSS Ho-oh Battle",
  "battleLegendaryRegisG5": "B2W2 Legendary Titan Battle",
  "battleLegendaryRegisG6": "ORAS Legendary Titan Battle",
  "battleLegendaryGroKyo": "ORAS Groudon & Kyogre Battle",
  "battleLegendaryRayquaza": "ORAS Rayquaza Battle",
  "battleLegendaryDeoxys": "ORAS Deoxys Battle",
  "battleLegendaryLakeTrio": "ORAS Lake Guardians Battle",
  "battleLegendarySinnoh": "ORAS Sinnoh Legendary Battle",
  "battleLegendaryDiaPal": "ORAS Dialga & Palkia Battle",
  "battleLegendaryOriginForme": "LA Origin Dialga & Palkia Battle",
  "battleLegendaryGiratina": "ORAS Giratina Battle",
  "battleLegendaryArceus": "HGSS Arceus Battle",
  "battleLegendaryUnova": "BW Unova Legendary Battle",
  "battleLegendaryKyurem": "BW Kyurem Battle",
  "battleLegendaryResZek": "BW Reshiram & Zekrom Battle",
  "battleLegendaryXernYvel": "XY Xerneas & Yveltal Battle",
  "battleLegendaryTapu": "SM Tapu Battle",
  "battleLegendarySolLun": "SM Solgaleo & Lunala Battle",
  "battleLegendaryUb": "SM Ultra Beast Battle",
  "battleLegendaryDuskDawn": "USUM Dusk Mane & Dawn Wings Necrozma Battle",
  "battleLegendaryUltraNec": "USUM Ultra Necrozma Battle",
  "battleLegendaryZacZam": "SWSH Zacian & Zamazenta Battle",
  "battleLegendaryEternatusP1": "SWSH Eternatus Battle",
  "battleLegendaryEternatusP2": "SWSH Eternamax Eternatus Battle",
  "battleLegendaryGlasSpec": "SWSH Glastrier & Spectrier Battle",
  "battleLegendaryCalyrex": "SWSH Calyrex Battle",
  "battleLegendaryRiders": "SWSH Ice & Shadow Rider Calyrex Battle",
  "battleLegendaryBirdsGalar": "SWSH Galarian Legendary Birds Battle",
  "battleLegendaryRuinous": "SV Treasures of Ruin Battle",
  "battleLegendaryKorMir": "SV Depths of Area Zero Battle",
  "battleLegendaryLoyalThree": "SV Loyal Three Battle",
  "battleLegendaryOgerpon": "SV Ogerpon Battle",
  "battleLegendaryTerapagos": "SV Terapagos Battle",
  "battleLegendaryPecharunt": "SV Pecharunt Battle",
  "battleRival": "BW Rival Battle",
  "battleRival2": "BW N Battle",
  "battleRival3": "BW Final N Battle",
  "battleTrainer": "BW Trainer Battle",
  "battleWild": "BW Wild Battle",
  "battleWildStrong": "BW Strong Wild Battle",
  "endSummit": "PMD RTDX Sky Tower Summit",
  "battleRocketGrunt": "HGSS Team Rocket Battle",
  "battleAquaMagmaGrunt": "ORAS Team Aqua & Magma Battle",
  "battleGalacticGrunt": "BDSP Team Galactic Battle",
  "battlePlasmaGrunt": "BW Team Plasma Battle",
  "battleFlareGrunt": "XY Team Flare Battle",
  "battleAetherGrunt": "SM Aether Foundation Battle",
  "battleSkullGrunt": "SM Team Skull Battle",
  "battleMacroGrunt": "SWSH Trainer Battle",
  "battleStarGrunt": "SV Team Star Battle",
  "battleGalacticAdmin": "BDSP Team Galactic Admin Battle",
  "battleColress": "BW2 Colress Battle",
  "battleSkullAdmin": "SM Team Skull Admin Battle",
  "battleOleana": "SWSH Oleana Battle",
  "battleStarAdmin": "SV Team Star Boss Battle",
  "battleRocketBoss": "USUM Giovanni Battle",
  "battleAquaMagmaBoss": "ORAS Archie & Maxie Battle",
  "battleGalacticBoss": "BDSP Cyrus Battle",
  "battlePlasmaBoss": "B2W2 Ghetsis Battle",
  "battleFlareBoss": "XY Lysandre Battle",
  "battleAetherBoss": "SM Lusamine Battle",
  "battleSkullBoss": "SM Guzma Battle",
  "battleMacroBoss": "SWSH Rose Battle",
  "battleStarBoss": "SV Cassiopeia Battle",

  "abyss": "Firel - Penumbra Chasm",
  "badlands": "PMD EoS Barren Valley",
  "beach": "PMD EoS Drenched Bluff",
  "cave": "PMD EoS Sky Peak Cave",
  "constructionSite": "PMD EoS Boulder Quarry",
  "desert": "Firel - Far Sands",
  "dojo": "PMD EoS Marowak Dojo",
  "end": "Firel - Darkest Day",
  "factory": "PMD EoS Concealed Ruins",
  "fairyCave": "Andr06 - Enchanted Cave",
  "forest": "Andr06 - Rogue’s Echoes",
  "grass": "PMD EoS Apple Woods",
  "graveyard": "Firel - Faller",
  "iceCave": "Firel - -50°C",
  "island": "PMD EoS Craggy Coast",
  "jungle": "Lmz - Jungle",
  "laboratory": "Firel - Laboratory",
  "lake": "Lmz - Lake",
  "meadow": "PMD EoS Sky Peak Forest",
  "metropolis": "Firel - Metropolis",
  "mountain": "PMD EoS Mt. Horn",
  "plains": "Firel - Route 888",
  "powerPlant": "Firel - The Klink",
  "ruins": "Lmz - Ancient Ruins",
  "sea": "Andr06 - Marine Mystique",
  "seabed": "Firel - Seabed",
  "slum": "Andr06 - Sneaky Snom",
  "snowyForest": "Bird_Obsession - Silent Snowfall",
  "space": "Firel - Aether",
  "swamp": "PMD EoS Surrounded Sea",
  "tallGrass": "PMD EoS Foggy Forest",
  "temple": "PMD EoS Aegis Cave",
  "town": "PMD EoS Random Dungeon Theme 3",
  "volcano": "Firel - Twisturn Volcano",
  "wasteland": "Leavannite - Empty Dream",
  "encounterAceTrainer": "BW Trainers’ Eyes Meet (Ace Trainer)",
  "encounterBackpacker": "BW Trainers’ Eyes Meet (Backpacker)",
  "encounterClerk": "BW Trainers’ Eyes Meet (Clerk)",
  "encounterCyclist": "BW Trainers’ Eyes Meet (Cyclist)",
  "encounterLass": "BW Trainers’ Eyes Meet (Lass)",
  "encounterParasolLady": "BW Trainers’ Eyes Meet (Parasol Lady)",
  "encounterPokefan": "BW Trainers’ Eyes Meet (Poke Fan)",
  "encounterPsychic": "BW Trainers’ Eyes Meet (Psychic)",
  "encounterRich": "BW Trainers’ Eyes Meet (Gentleman)",
  "encounterRival": "BW Cheren",
  "encounterRoughneck": "BW Trainers’ Eyes Meet (Roughneck)",
  "encounterScientist": "BW Trainers’ Eyes Meet (Scientist)",
  "encounterTwins": "BW Trainers’ Eyes Meet (Twins)",
  "encounterYoungster": "BW Trainers’ Eyes Meet (Youngster)",
  "heal": "BW Pokémon Heal",
  "menu": "PMD EoS Welcome to the World of Pokémon!",
  "title": "Firel - PokéRogue",
  "winterTitle": "Andr06 - Cozy Christmas",

  "mysteryEncounterWeirdDream": "PMD EoS Temporal Spire",
  "mysteryEncounterFunAndGames": "PMD EoS Guildmaster Wigglytuff",
  "mysteryEncounterGen5Gts": "BW GTS",
  "mysteryEncounterGen6Gts": "XY GTS",
  "mysteryEncounterDelibirdy": "Firel - DeliDelivery!"
}
