{
  "youngster": {
    "encounter": {
      "1": "Hej, chcesz powalczyć?",
      "2": "Też jesteś nowym trenerem?",
      "2_female": "Też jesteś nową trenerką?",
      "3": "Hej, nie widziałem cię tu wcześniej. Powalczmy!",
      "4": "Właśnie przegrałem, więc szukam więcej Pokémonów.\nCzekaj! Nie wyglądasz na mocnego! No dawaj, walczymy!",
      "4_female": "Właśnie przegrałam, więc szukam więcej Pokémonów.\nCzekaj! Nie wyglądasz na mocnego! No dawaj, walczymy!",
      "5": "Spotkaliśmy się wcześniej? Bo w sumie nie pamiętam. W każdym razie miło cię poznać!",
      "6": "No dobra, dawaj!",
      "7": "Uwaga nadchodzę! Pokażę ci moją siłę!",
      "9": "Nie ma co tracić czasu na powitania. Powiedz jak będziesz gotowy!",
      "9_female": "Nie ma co tracić czasu na powitania. Powiedz jak będziesz gotowy!",
      "10": "Nie opuszczaj gardy albo będziesz płakać jak pokona cię dzieciak.",
      "12": "Dobrze ci idzie! Ale odtąd będzie tylko trudniej.",
      "12_female": "Dobrze ci idzie! Ale odtąd będzie tylko trudniej.",
      "13": "Tutaj bitwy się nie kończą! Witaj w nieskończonym świecie!",
      "13_female": "Tutaj bitwy się nie kończą! Witaj w nieskończonym świecie!"
    },
    "victory": {
      "1": "Wow! Ale ty silny jesteś!",
      "1_female": "Wow! Ale ty silna jesteś!",
      "2": "Nie miałem szans, nie?",
      "3": "Znajdę cię jak dorosnę i wtedy cię pokonam!",
      "4": "Eh. Nie mam już Pokémonów.",
      "5": "Nie… NIEMOŻLIWE! Jak mogłem znowu przegrać…",
      "5_female": "Nie… NIEMOŻLIWE! Jak mogłam znowu przegrać…",
      "6": "No nie! Przegrałem!",
      "7": "Wow! Jesteś wspaniały! Opadła mi szczęka!",
      "8": "Ale… Jak to… Przecież moje Pokémony i ja jesteśmy najsilniejsi…",
      "9": "Następnym razem nie przegram! Powalczmy jeszcze kiedyś!",
      "10": "Spokojnie! Nie widzisz że jestem tylko dzieckiem! To nie fair, że tak poszedłeś na całość!",
      "11": "Twoje Pokémony są niesamowite! Chcesz się wymienić?",
      "12": "Trochę mnie wcześniej poniosło ale o jakiej pracy ja mówiłem?"
    }
  }
}
