{
  "blue_red_double": {
    "encounter": {
      "1": "Blu: Hey Rosso, facciamogli vedere di cosa siamo fatti!$Rosso: …$Blu: Questa è la potenza di Biancavilla!"
    },
    "victory": {
      "1": "Blu: Questa è stata una grande battaglia!$Rosso: …"
    }
  },
  "red_blue_double": {
    "encounter": {
      "1": "Rosso: …!$Blu: Lui non è molto loquace.$Blu: Ma non farti fregare! Dopo tutto è un Campione Pokémon!"
    },
    "victory": {
      "1": "Rosso: …!$Blu: La prossima volta ti sconfiggeremo!"
    }
  }
}
