{
  "bulbasaur_category": "Pokémon Semilla",
  "ivysaur_category": "Pokémon Semilla",
  "venusaur_category": "Pokémon Semilla",
  "charmander_category": "Pokémon Lagartija",
  "charmeleon_category": "Pokémon Llama",
  "charizard_category": "Pokémon Llama",
  "squirtle_category": "Pokémon Tortuguita",
  "wartortle_category": "Pokémon Tortuga",
  "blastoise_category": "Pokémon Armazón",
  "caterpie_category": "Pokémon Gusano",
  "metapod_category": "Pokémon Capullo",
  "butterfree_category": "Pokémon Mariposa",
  "weedle_category": "Pokémon Oruga",
  "kakuna_category": "Pokémon Capullo",
  "beedrill_category": "Pokémon Abeja Veneno",
  "pidgey_category": "Pokémon Pajarito",
  "pidgeotto_category": "Pokémon Pájaro",
  "pidgeot_category": "Pokémon Pájaro",
  "rattata_category": "Pokémon Ratón",
  "raticate_category": "Pokémon Ratón",
  "spearow_category": "Pokémon Pajarito",
  "fearow_category": "Pokémon Picotazo",
  "ekans_category": "Pokémon Serpiente",
  "arbok_category": "Pokémon Cobra",
  "pikachu_category": "Pokémon Ratón",
  "raichu_category": "Pokémon Ratón",
  "sandshrew_category": "Pokémon Ratón",
  "sandslash_category": "Pokémon Ratón",
  "nidoran_f_category": "Pokémon Púa Venenosa",
  "nidorina_category": "Pokémon Púa Venenosa",
  "nidoqueen_category": "Pokémon Taladro",
  "nidoran_m_category": "Pokémon Púa Venenosa",
  "nidorino_category": "Pokémon Púa Venenosa",
  "nidoking_category": "Pokémon Taladro",
  "clefairy_category": "Pokémon Hada",
  "clefable_category": "Pokémon Hada",
  "vulpix_category": "Pokémon Zorro",
  "ninetales_category": "Pokémon Zorro",
  "jigglypuff_category": "Pokémon Globo",
  "wigglytuff_category": "Pokémon Globo",
  "zubat_category": "Pokémon Murciélago",
  "golbat_category": "Pokémon Murciélago",
  "oddish_category": "Pokémon Maleza",
  "gloom_category": "Pokémon Maleza",
  "vileplume_category": "Pokémon Flor",
  "paras_category": "Pokémon Hongo",
  "parasect_category": "Pokémon Hongo",
  "venonat_category": "Pokémon Insecto",
  "venomoth_category": "Pokémon Polilla Venenosa",
  "diglett_category": "Pokémon Topo",
  "dugtrio_category": "Pokémon Topo",
  "meowth_category": "Pokémon Gato Arañazo",
  "persian_category": "Pokémon Sofistigato",
  "psyduck_category": "Pokémon Pato",
  "golduck_category": "Pokémon Pato",
  "mankey_category": "Pokémon Mono Cerdo",
  "primeape_category": "Pokémon Mono Cerdo",
  "growlithe_category": "Pokémon Perrito",
  "arcanine_category": "Pokémon Leyenda",
  "poliwag_category": "Pokémon Renacuajo",
  "poliwhirl_category": "Pokémon Renacuajo",
  "poliwrath_category": "Pokémon Renacuajo",
  "abra_category": "Pokémon Psi",
  "kadabra_category": "Pokémon Psi",
  "alakazam_category": "Pokémon Psi",
  "machop_category": "Pokémon Superpoder",
  "machoke_category": "Pokémon Superpoder",
  "machamp_category": "Pokémon Superpoder",
  "bellsprout_category": "Pokémon Flor",
  "weepinbell_category": "Pokémon Atrapamoscas",
  "victreebel_category": "Pokémon Atrapamoscas",
  "tentacool_category": "Pokémon Medusa",
  "tentacruel_category": "Pokémon Medusa",
  "geodude_category": "Pokémon Roca",
  "graveler_category": "Pokémon Roca",
  "golem_category": "Pokémon Megatón",
  "ponyta_category": "Pokémon Corcel Fuego",
  "rapidash_category": "Pokémon Corcel Fuego",
  "slowpoke_category": "Pokémon Atontado",
  "slowbro_category": "Pokémon Ermitaño",
  "magnemite_category": "Pokémon Imán",
  "magneton_category": "Pokémon Imán",
  "farfetchd_category": "Pokémon Pato Salvaje",
  "doduo_category": "Pokémon Ave Gemela",
  "dodrio_category": "Pokémon Ave Triple",
  "seel_category": "Pokémon León Marino",
  "dewgong_category": "Pokémon León Marino",
  "grimer_category": "Pokémon Lodo",
  "muk_category": "Pokémon Lodo",
  "shellder_category": "Pokémon Bivalvo",
  "cloyster_category": "Pokémon Bivalvo",
  "gastly_category": "Pokémon Gas",
  "haunter_category": "Pokémon Gas",
  "gengar_category": "Pokémon Sombra",
  "onix_category": "Pokémon Serpiente Roca",
  "drowzee_category": "Pokémon Hipnosis",
  "hypno_category": "Pokémon Hipnosis",
  "krabby_category": "Pokémon Cangrejo",
  "kingler_category": "Pokémon Pinza",
  "voltorb_category": "Pokémon Bola",
  "electrode_category": "Pokémon Bola",
  "exeggcute_category": "Pokémon Huevo",
  "exeggutor_category": "Pokémon Coco",
  "cubone_category": "Pokémon Solitario",
  "marowak_category": "Pokémon Apilahueso",
  "hitmonlee_category": "Pokémon Patada",
  "hitmonchan_category": "Pokémon Puñetazo",
  "lickitung_category": "Pokémon Lametazo",
  "koffing_category": "Pokémon Gas Venenoso",
  "weezing_category": "Pokémon Gas Venenoso",
  "rhyhorn_category": "Pokémon Punzante",
  "rhydon_category": "Pokémon Taladro",
  "chansey_category": "Pokémon Huevo",
  "tangela_category": "Pokémon Enredadera",
  "kangaskhan_category": "Pokémon Maternal",
  "horsea_category": "Pokémon Dragón",
  "seadra_category": "Pokémon Dragón",
  "goldeen_category": "Pokémon Pez Dorado",
  "seaking_category": "Pokémon Pez Dorado",
  "staryu_category": "Pokémon Estrella",
  "starmie_category": "Pokémon Misterioso",
  "mr_mime_category": "Pokémon Barrera",
  "scyther_category": "Pokémon Mantis",
  "jynx_category": "Pokémon Forma Humana",
  "electabuzz_category": "Pokémon Eléctrico",
  "magmar_category": "Pokémon Escupefuego",
  "pinsir_category": "Pokémon Escarabajo",
  "tauros_category": "Pokémon Toro Bravo",
  "magikarp_category": "Pokémon Pez",
  "gyarados_category": "Pokémon Atrocidad",
  "lapras_category": "Pokémon Transporte",
  "ditto_category": "Pokémon Transformación",
  "eevee_category": "Pokémon Evolución",
  "vaporeon_category": "Pokémon Burbuja",
  "jolteon_category": "Pokémon Relámpago",
  "flareon_category": "Pokémon Llama",
  "porygon_category": "Pokémon Virtual",
  "omanyte_category": "Pokémon Espiral",
  "omastar_category": "Pokémon Espiral",
  "kabuto_category": "Pokémon Armazón",
  "kabutops_category": "Pokémon Armazón",
  "aerodactyl_category": "Pokémon Fósil",
  "snorlax_category": "Pokémon Dormilón",
  "articuno_category": "Pokémon Congelación",
  "zapdos_category": "Pokémon Eléctrico",
  "moltres_category": "Pokémon Llama",
  "dratini_category": "Pokémon Dragón",
  "dragonair_category": "Pokémon Dragón",
  "dragonite_category": "Pokémon Dragón",
  "mewtwo_category": "Pokémon Genético",
  "mew_category": "Pokémon Nueva Especie",

  "chikorita_category": "Pokémon Hoja",
  "bayleef_category": "Pokémon Hoja",
  "meganium_category": "Pokémon Planta",
  "cyndaquil_category": "Pokémon Ratón de Fuego",
  "quilava_category": "Pokémon Volcán",
  "typhlosion_category": "Pokémon Volcán",
  "totodile_category": "Pokémon Fauces",
  "croconaw_category": "Pokémon Fauces",
  "feraligatr_category": "Pokémon Fauces",
  "sentret_category": "Pokémon Explorador",
  "furret_category": "Pokémon Cuerpo Alargado",
  "hoothoot_category": "Pokémon Búho",
  "noctowl_category": "Pokémon Búho",
  "ledyba_category": "Pokémon Cinco Estrellas",
  "ledian_category": "Pokémon Cinco Estrellas",
  "spinarak_category": "Pokémon Escupehilo",
  "ariados_category": "Pokémon Pata Larga",
  "crobat_category": "Pokémon Murciélago",
  "chinchou_category": "Pokémon Pejesapo",
  "lanturn_category": "Pokémon Luz",
  "pichu_category": "Pokémon Ratoncito",
  "cleffa_category": "Pokémon Estrella",
  "igglybuff_category": "Pokémon Globo",
  "togepi_category": "Pokémon Bolita Púas",
  "togetic_category": "Pokémon Felicidad",
  "natu_category": "Pokémon Pajarito",
  "xatu_category": "Pokémon Místico",
  "mareep_category": "Pokémon Lana",
  "flaaffy_category": "Pokémon Lana",
  "ampharos_category": "Pokémon Luz",
  "bellossom_category": "Pokémon Flor",
  "marill_category": "Pokémon Ratón de Agua",
  "azumarill_category": "Pokémon Conejo de Agua",
  "sudowoodo_category": "Pokémon Imitación",
  "politoed_category": "Pokémon Rana",
  "hoppip_category": "Pokémon Diente León",
  "skiploom_category": "Pokémon Diente León",
  "jumpluff_category": "Pokémon Diente León",
  "aipom_category": "Pokémon Cola Larga",
  "sunkern_category": "Pokémon Semilla",
  "sunflora_category": "Pokémon Sol",
  "yanma_category": "Pokémon Ala Clara",
  "wooper_category": "Pokémon Acuapez",
  "quagsire_category": "Pokémon Acuapez",
  "espeon_category": "Pokémon Sol",
  "umbreon_category": "Pokémon Luz Lunar",
  "murkrow_category": "Pokémon Oscuridad",
  "slowking_category": "Pokémon Regio",
  "misdreavus_category": "Pokémon Chirrido",
  "unown_category": "Pokémon Símbolo",
  "wobbuffet_category": "Pokémon Paciencia",
  "girafarig_category": "Pokémon Gran Cuello",
  "pineco_category": "Pokémon Orusaquito",
  "forretress_category": "Pokémon Orusaquito",
  "dunsparce_category": "Pokémon Serpiente Tierra",
  "gligar_category": "Pokémon Escorpiala",
  "steelix_category": "Pokémon Serpiente Férrea",
  "snubbull_category": "Pokémon Hada",
  "granbull_category": "Pokémon Hada",
  "qwilfish_category": "Pokémon Globo",
  "scizor_category": "Pokémon Pinza",
  "shuckle_category": "Pokémon Moho",
  "heracross_category": "Pokémon Cuerno",
  "sneasel_category": "Pokémon Garra Filo",
  "teddiursa_category": "Pokémon Osito",
  "ursaring_category": "Pokémon Hibernación",
  "slugma_category": "Pokémon Lava",
  "magcargo_category": "Pokémon Lava",
  "swinub_category": "Pokémon Cerdo",
  "piloswine_category": "Pokémon Puerco",
  "corsola_category": "Pokémon Coral",
  "remoraid_category": "Pokémon Reactor",
  "octillery_category": "Pokémon Reactor",
  "delibird_category": "Pokémon Repartidor",
  "mantine_category": "Pokémon Cometa",
  "skarmory_category": "Pokémon Coraza Ave",
  "houndour_category": "Pokémon Siniestro",
  "houndoom_category": "Pokémon Siniestro",
  "kingdra_category": "Pokémon Dragón",
  "phanpy_category": "Pokémon Narizota",
  "donphan_category": "Pokémon Coraza",
  "porygon2_category": "Pokémon Virtual",
  "stantler_category": "Pokémon Gran Cuerno",
  "smeargle_category": "Pokémon Pintor",
  "tyrogue_category": "Pokémon Peleonero",
  "hitmontop_category": "Pokémon Boca Abajo",
  "smoochum_category": "Pokémon Beso",
  "elekid_category": "Pokémon Eléctrico",
  "magby_category": "Pokémon Brasaviva",
  "miltank_category": "Pokémon Vaca Lechera",
  "blissey_category": "Pokémon Felicidad",
  "raikou_category": "Pokémon Trueno",
  "entei_category": "Pokémon Volcán",
  "suicune_category": "Pokémon Aurora",
  "larvitar_category": "Pokémon Piel Rocosa",
  "pupitar_category": "Pokémon Caparazón",
  "tyranitar_category": "Pokémon Coraza",
  "lugia_category": "Pokémon Buceo",
  "ho_oh_category": "Pokémon Arcoíris",
  "celebi_category": "Pokémon Viajatiempo",

  "treecko_category": "Pokémon Geco del Bosque",
  "grovyle_category": "Pokémon Geco del Bosque",
  "sceptile_category": "Pokémon Bosque",
  "torchic_category": "Pokémon Polluelo",
  "combusken_category": "Pokémon Ave Corral",
  "blaziken_category": "Pokémon Llameante",
  "mudkip_category": "Pokémon Pez Lodo",
  "marshtomp_category": "Pokémon Pez Lodo",
  "swampert_category": "Pokémon Pez Lodo",
  "poochyena_category": "Pokémon Mordisco",
  "mightyena_category": "Pokémon Mordisco",
  "zigzagoon_category": "Pokémon Mapachito",
  "linoone_category": "Pokémon Lanzado",
  "wurmple_category": "Pokémon Gusano",
  "silcoon_category": "Pokémon Capullo",
  "beautifly_category": "Pokémon Mariposa",
  "cascoon_category": "Pokémon Capullo",
  "dustox_category": "Pokémon Polilla Venenosa",
  "lotad_category": "Pokémon Alga",
  "lombre_category": "Pokémon Alegre",
  "ludicolo_category": "Pokémon Optimista",
  "seedot_category": "Pokémon Bellota",
  "nuzleaf_category": "Pokémon Astuto",
  "shiftry_category": "Pokémon Malvado",
  "taillow_category": "Pokémon Golondrinita",
  "swellow_category": "Pokémon Golondrina",
  "wingull_category": "Pokémon Gaviota",
  "pelipper_category": "Pokémon Ave de Agua",
  "ralts_category": "Pokémon Sensible",
  "kirlia_category": "Pokémon Emoción",
  "gardevoir_category": "Pokémon Envolvente",
  "surskit_category": "Pokémon Zapatero",
  "masquerain_category": "Pokémon Globo Ocular",
  "shroomish_category": "Pokémon Hongo",
  "breloom_category": "Pokémon Hongo",
  "slakoth_category": "Pokémon Haragán",
  "vigoroth_category": "Pokémon Mono Feroz",
  "slaking_category": "Pokémon Holgazán",
  "nincada_category": "Pokémon Aprendiz",
  "ninjask_category": "Pokémon Ninja",
  "shedinja_category": "Pokémon Muda",
  "whismur_category": "Pokémon Susurro",
  "loudred_category": "Pokémon Chillón",
  "exploud_category": "Pokémon Escandaloso",
  "makuhita_category": "Pokémon Valiente",
  "hariyama_category": "Pokémon Empuje",
  "azurill_category": "Pokémon Bola de Agua",
  "nosepass_category": "Pokémon Brújula",
  "skitty_category": "Pokémon Gatito",
  "delcatty_category": "Pokémon Cursi",
  "sableye_category": "Pokémon Oscuridad",
  "mawile_category": "Pokémon Tramposo",
  "aron_category": "Pokémon Armadura de Hierro",
  "lairon_category": "Pokémon Armadura de Hierro",
  "aggron_category": "Pokémon Armadura de Hierro",
  "meditite_category": "Pokémon Meditador",
  "medicham_category": "Pokémon Meditador",
  "electrike_category": "Pokémon Relámpago",
  "manectric_category": "Pokémon Descarga",
  "plusle_category": "Pokémon Ánimo",
  "minun_category": "Pokémon Ánimo",
  "volbeat_category": "Pokémon Luciérnaga",
  "illumise_category": "Pokémon Luciérnaga",
  "roselia_category": "Pokémon Espina",
  "gulpin_category": "Pokémon Estómago",
  "swalot_category": "Pokémon Bolsa Veneno",
  "carvanha_category": "Pokémon Feroz",
  "sharpedo_category": "Pokémon Brutal",
  "wailmer_category": "Pokémon Ballenabola",
  "wailord_category": "Pokémon Flotaballena",
  "numel_category": "Pokémon Torpe",
  "camerupt_category": "Pokémon Estallido",
  "torkoal_category": "Pokémon Carbón",
  "spoink_category": "Pokémon Saltarín",
  "grumpig_category": "Pokémon Manipulador",
  "spinda_category": "Pokémon Pandamanchas",
  "trapinch_category": "Pokémon Hormiga León",
  "vibrava_category": "Pokémon Vibrante",
  "flygon_category": "Pokémon Místico",
  "cacnea_category": "Pokémon Cactus",
  "cacturne_category": "Pokémon Espantajo",
  "swablu_category": "Pokémon Ave de Algodón",
  "altaria_category": "Pokémon Cantor",
  "zangoose_category": "Pokémon Gato Hurón",
  "seviper_category": "Pokémon Colmillos",
  "lunatone_category": "Pokémon Meteorito",
  "solrock_category": "Pokémon Meteorito",
  "barboach_category": "Pokémon Bigotudo",
  "whiscash_category": "Pokémon Bigotudo",
  "corphish_category": "Pokémon Rufián",
  "crawdaunt_category": "Pokémon Granuja",
  "baltoy_category": "Pokémon Muñeca de Barro",
  "claydol_category": "Pokémon Muñeca de Barro",
  "lileep_category": "Pokémon Lirio de Mar",
  "cradily_category": "Pokémon Percebe",
  "anorith_category": "Pokémon Camarón",
  "armaldo_category": "Pokémon Armadura",
  "feebas_category": "Pokémon Pez",
  "milotic_category": "Pokémon Tierno",
  "castform_category": "Pokémon Clima",
  "kecleon_category": "Pokémon Camaleónico",
  "shuppet_category": "Pokémon Títere",
  "banette_category": "Pokémon Marioneta",
  "duskull_category": "Pokémon Réquiem",
  "dusclops_category": "Pokémon Atrayente",
  "tropius_category": "Pokémon Fruto",
  "chimecho_category": "Pokémon Campanilla",
  "absol_category": "Pokémon Catástrofe",
  "wynaut_category": "Pokémon Radiante",
  "snorunt_category": "Pokémon Gorro de Nieve",
  "glalie_category": "Pokémon Cara",
  "spheal_category": "Pokémon Aplauso",
  "sealeo_category": "Pokémon Rodabola",
  "walrein_category": "Pokémon Rompehielo",
  "clamperl_category": "Pokémon Bivalvo",
  "huntail_category": "Pokémon Abisal",
  "gorebyss_category": "Pokémon Mar del Sur",
  "relicanth_category": "Pokémon Longevo",
  "luvdisc_category": "Pokémon Cita",
  "bagon_category": "Pokémon Cabeza Roca",
  "shelgon_category": "Pokémon Resistencia",
  "salamence_category": "Pokémon Dragón",
  "beldum_category": "Pokémon Bola de Hierro",
  "metang_category": "Pokémon Garra de Hierro",
  "metagross_category": "Pokémon Patas de Hierro",
  "regirock_category": "Pokémon Cumbre de Roca",
  "regice_category": "Pokémon Iceberg",
  "registeel_category": "Pokémon Hierro",
  "latias_category": "Pokémon Eón",
  "latios_category": "Pokémon Eón",
  "kyogre_category": "Pokémon Cuenca de Mar",
  "groudon_category": "Pokémon Continente",
  "rayquaza_category": "Pokémon Cielo",
  "jirachi_category": "Pokémon Deseo",
  "deoxys_category": "Pokémon ADN",

  "turtwig_category": "Pokémon Hojita",
  "grotle_category": "Pokémon Arboleda",
  "torterra_category": "Pokémon Continente",
  "chimchar_category": "Pokémon Chimpancé",
  "monferno_category": "Pokémon Juguetón",
  "infernape_category": "Pokémon Llama",
  "piplup_category": "Pokémon Pingüino",
  "prinplup_category": "Pokémon Pingüino",
  "empoleon_category": "Pokémon Emperador",
  "starly_category": "Pokémon Estornino",
  "staravia_category": "Pokémon Estornino",
  "staraptor_category": "Pokémon Depredador",
  "bidoof_category": "Pokémon Gran Ratón",
  "bibarel_category": "Pokémon Castor",
  "kricketot_category": "Pokémon Grillo",
  "kricketune_category": "Pokémon Grillo",
  "shinx_category": "Pokémon Flash",
  "luxio_category": "Pokémon Chispa",
  "luxray_category": "Pokémon Chispa Ojos",
  "budew_category": "Pokémon Brote",
  "roserade_category": "Pokémon Ramillete",
  "cranidos_category": "Pokémon Cabezazo",
  "rampardos_category": "Pokémon Cabezazo",
  "shieldon_category": "Pokémon Escudo",
  "bastiodon_category": "Pokémon Escudo",
  "burmy_category": "Pokémon Orusaquito",
  "wormadam_category": "Pokémon Orusaquito",
  "mothim_category": "Pokémon Polilla",
  "combee_category": "Pokémon Abejita",
  "vespiquen_category": "Pokémon Colmena",
  "pachirisu_category": "Pokémon Electroardi",
  "buizel_category": "Pokémon Nutria Marina",
  "floatzel_category": "Pokémon Nutria Marina",
  "cherubi_category": "Pokémon Cereza",
  "cherrim_category": "Pokémon Floración",
  "shellos_category": "Pokémon Babosa Marina",
  "gastrodon_category": "Pokémon Babosa Marina",
  "ambipom_category": "Pokémon Cola Larga",
  "drifloon_category": "Pokémon Globo",
  "drifblim_category": "Pokémon Dirigible",
  "buneary_category": "Pokémon Conejo",
  "lopunny_category": "Pokémon Conejo",
  "mismagius_category": "Pokémon Mágico",
  "honchkrow_category": "Pokémon Gran Jefe",
  "glameow_category": "Pokémon Gastuto",
  "purugly_category": "Pokémon Tigre Gato",
  "chingling_category": "Pokémon Cascabel",
  "stunky_category": "Pokémon Mofeta",
  "skuntank_category": "Pokémon Mofeta",
  "bronzor_category": "Pokémon Bronce",
  "bronzong_category": "Pokémon Campana de Bronce",
  "bonsly_category": "Pokémon Bonsái",
  "mime_jr_category": "Pokémon Mimo",
  "happiny_category": "Pokémon Casita",
  "chatot_category": "Pokémon Corchea",
  "spiritomb_category": "Pokémon Prohibido",
  "gible_category": "Pokémon Terrascualo",
  "gabite_category": "Pokémon Cueva",
  "garchomp_category": "Pokémon Mach",
  "munchlax_category": "Pokémon Comelón",
  "riolu_category": "Pokémon Emanación",
  "lucario_category": "Pokémon Aura",
  "hippopotas_category": "Pokémon Hipo",
  "hippowdon_category": "Pokémon Peso Pesado",
  "skorupi_category": "Pokémon Escorpión",
  "drapion_category": "Pokémon Escorpiogro",
  "croagunk_category": "Pokémon Boca Tóxica",
  "toxicroak_category": "Pokémon Boca Tóxica",
  "carnivine_category": "Pokémon Cazainsectos",
  "finneon_category": "Pokémon Pez Ala",
  "lumineon_category": "Pokémon Neón",
  "mantyke_category": "Pokémon Cometa",
  "snover_category": "Pokémon Árbol Nieve",
  "abomasnow_category": "Pokémon Árbol Nieve",
  "weavile_category": "Pokémon Garra Filo",
  "magnezone_category": "Pokémon Magnético",
  "lickilicky_category": "Pokémon Lametazo",
  "rhyperior_category": "Pokémon Taladro",
  "tangrowth_category": "Pokémon Enredadera",
  "electivire_category": "Pokémon Rayo",
  "magmortar_category": "Pokémon Explosión",
  "togekiss_category": "Pokémon Festivo",
  "yanmega_category": "Pokémon Libélula",
  "leafeon_category": "Pokémon Vegetación",
  "glaceon_category": "Pokémon Nieve Fresca",
  "gliscor_category": "Pokémon Colmicorpio",
  "mamoswine_category": "Pokémon Doscolmillos",
  "porygon_z_category": "Pokémon Virtual",
  "gallade_category": "Pokémon Cuchilla",
  "probopass_category": "Pokémon Brújula",
  "dusknoir_category": "Pokémon Grilletes",
  "froslass_category": "Pokémon Tierra Fría",
  "rotom_category": "Pokémon Plasma",
  "uxie_category": "Pokémon Sabiduría",
  "mesprit_category": "Pokémon Emoción",
  "azelf_category": "Pokémon Voluntad",
  "dialga_category": "Pokémon Temporal",
  "palkia_category": "Pokémon Espacial",
  "heatran_category": "Pokémon Domo de Lava",
  "regigigas_category": "Pokémon Colosal",
  "giratina_category": "Pokémon Renegado",
  "cresselia_category": "Pokémon Lunar",
  "phione_category": "Pokémon Marino",
  "manaphy_category": "Pokémon Náutico",
  "darkrai_category": "Pokémon Oscuridad",
  "shaymin_category": "Pokémon Gratitud",
  "arceus_category": "Pokémon Alfa",

  "victini_category": "Pokémon Victoria",
  "snivy_category": "Pokémon Serpiente Planta",
  "servine_category": "Pokémon Serpiente Planta",
  "serperior_category": "Pokémon Realeza",
  "tepig_category": "Pokémon Cerdo de Fuego",
  "pignite_category": "Pokémon Cerdo de Fuego",
  "emboar_category": "Pokémon Cerdo Ígneo",
  "oshawott_category": "Pokémon Nutria",
  "dewott_category": "Pokémon Superación",
  "samurott_category": "Pokémon Majestuoso",
  "patrat_category": "Pokémon Explorador",
  "watchog_category": "Pokémon Alerta",
  "lillipup_category": "Pokémon Perrito",
  "herdier_category": "Pokémon Perro Fiel",
  "stoutland_category": "Pokémon Gran Corazón",
  "purrloin_category": "Pokémon Malicioso",
  "liepard_category": "Pokémon Cruel",
  "pansage_category": "Pokémon Mono Hierba",
  "simisage_category": "Pokémon Mono Espina",
  "pansear_category": "Pokémon Ardiente",
  "simisear_category": "Pokémon Lumbre",
  "panpour_category": "Pokémon Salpicadura",
  "simipour_category": "Pokémon Géiser",
  "munna_category": "Pokémon Comesueños",
  "musharna_category": "Pokémon Duermevela",
  "pidove_category": "Pokémon Pichón",
  "tranquill_category": "Pokémon Torcaz",
  "unfezant_category": "Pokémon Altanero",
  "blitzle_category": "Pokémon Electrizado",
  "zebstrika_category": "Pokémon Rayo",
  "roggenrola_category": "Pokémon Manto",
  "boldore_category": "Pokémon Mineral",
  "gigalith_category": "Pokémon Comprimido",
  "woobat_category": "Pokémon Murciélago",
  "swoobat_category": "Pokémon Galante",
  "drilbur_category": "Pokémon Topo",
  "excadrill_category": "Pokémon Subterráneo",
  "audino_category": "Pokémon Escucha",
  "timburr_category": "Pokémon Musculoso",
  "gurdurr_category": "Pokémon Musculoso",
  "conkeldurr_category": "Pokémon Musculoso",
  "tympole_category": "Pokémon Renacuajo",
  "palpitoad_category": "Pokémon Vibrante",
  "seismitoad_category": "Pokémon Vibrante",
  "throh_category": "Pokémon Judo",
  "sawk_category": "Pokémon Karate",
  "sewaddle_category": "Pokémon Sastre",
  "swadloon_category": "Pokémon Hojaenvuelto",
  "leavanny_category": "Pokémon Cultivador",
  "venipede_category": "Pokémon Ciempiés",
  "whirlipede_category": "Pokémon Curlípodo",
  "scolipede_category": "Pokémon Megaciempiés",
  "cottonee_category": "Pokémon Nube Algodón",
  "whimsicott_category": "Pokémon Vuelalviento",
  "petilil_category": "Pokémon Bulbo",
  "lilligant_category": "Pokémon Floreciente",
  "basculin_category": "Pokémon Hostil",
  "sandile_category": "Pokémon Desierdrilo",
  "krokorok_category": "Pokémon Desierdrilo",
  "krookodile_category": "Pokémon Intimidación",
  "darumaka_category": "Pokémon Daruma",
  "darmanitan_category": "Pokémon Candente",
  "maractus_category": "Pokémon Cactus",
  "dwebble_category": "Pokémon Casapiedra",
  "crustle_category": "Pokémon Casarroca",
  "scraggy_category": "Pokémon Mudapiel",
  "scrafty_category": "Pokémon Vándalo",
  "sigilyph_category": "Pokémon Pseudopájaro",
  "yamask_category": "Pokémon Espíritu",
  "cofagrigus_category": "Pokémon Sepultura",
  "tirtouga_category": "Pokémon Pretortuga",
  "carracosta_category": "Pokémon Pretortuga",
  "archen_category": "Pokémon Protopájaro",
  "archeops_category": "Pokémon Protopájaro",
  "trubbish_category": "Pokémon Bolsa de Basura",
  "garbodor_category": "Pokémon Basurero",
  "zorua_category": "Pokémon Zorro Pillo",
  "zoroark_category": "Pokémon Disfrazorro",
  "minccino_category": "Pokémon Chinchilla",
  "cinccino_category": "Pokémon Bufanda",
  "gothita_category": "Pokémon Obsesión",
  "gothorita_category": "Pokémon Manipulador",
  "gothitelle_category": "Pokémon Astro",
  "solosis_category": "Pokémon Célula",
  "duosion_category": "Pokémon Mitosis",
  "reuniclus_category": "Pokémon Ampliación",
  "ducklett_category": "Pokémon Ave de Agua",
  "swanna_category": "Pokémon Cisne",
  "vanillite_category": "Pokémon Nieve Fresca",
  "vanillish_category": "Pokémon Nieve Helada",
  "vanilluxe_category": "Pokémon Nieve Gélida",
  "deerling_category": "Pokémon Estacional",
  "sawsbuck_category": "Pokémon Estacional",
  "emolga_category": "Pokémon Vuelardilla",
  "karrablast_category": "Pokémon Bocado",
  "escavalier_category": "Pokémon Caballería",
  "foongus_category": "Pokémon Hongo",
  "amoonguss_category": "Pokémon Hongo",
  "frillish_category": "Pokémon Ingrávido",
  "jellicent_category": "Pokémon Ingrávido",
  "alomomola_category": "Pokémon Socorrista",
  "joltik_category": "Pokémon Adjunto",
  "galvantula_category": "Pokémon Electroaraña",
  "ferroseed_category": "Pokémon Fruto Espina",
  "ferrothorn_category": "Pokémon Bola Espina",
  "klink_category": "Pokémon Engranaje",
  "klang_category": "Pokémon Engranaje",
  "klinklang_category": "Pokémon Engranaje",
  "tynamo_category": "Pokémon Electropez",
  "eelektrik_category": "Pokémon Electropez",
  "eelektross_category": "Pokémon Electropez",
  "elgyem_category": "Pokémon Cerebral",
  "beheeyem_category": "Pokémon Cerebral",
  "litwick_category": "Pokémon Vela",
  "lampent_category": "Pokémon Farolito",
  "chandelure_category": "Pokémon Señuelo",
  "axew_category": "Pokémon Colmillo",
  "fraxure_category": "Pokémon Mandíbula Hacha",
  "haxorus_category": "Pokémon Mandíbula Hacha",
  "cubchoo_category": "Pokémon Congelador",
  "beartic_category": "Pokémon Congelado",
  "cryogonal_category": "Pokémon Cristal",
  "shelmet_category": "Pokémon Caracol",
  "accelgor_category": "Pokémon Sincaparazón",
  "stunfisk_category": "Pokémon Trampa",
  "mienfoo_category": "Pokémon Arte Marcial",
  "mienshao_category": "Pokémon Arte Marcial",
  "druddigon_category": "Pokémon Cueva",
  "golett_category": "Pokémon Autómata",
  "golurk_category": "Pokémon Autómata",
  "pawniard_category": "Pokémon Espada Afilada",
  "bisharp_category": "Pokémon Filo",
  "bouffalant_category": "Pokémon Embestauro",
  "rufflet_category": "Pokémon Aguilucho",
  "braviary_category": "Pokémon Valeroso",
  "vullaby_category": "Pokémon Pañal",
  "mandibuzz_category": "Pokémon Buitre de Huesos",
  "heatmor_category": "Pokémon Hormiguero",
  "durant_category": "Pokémon Hormigacero",
  "deino_category": "Pokémon Tosco",
  "zweilous_category": "Pokémon Hostil",
  "hydreigon_category": "Pokémon Brutal",
  "larvesta_category": "Pokémon Antorcha",
  "volcarona_category": "Pokémon Sol",
  "cobalion_category": "Pokémon Tesón de Acero",
  "terrakion_category": "Pokémon Gruta",
  "virizion_category": "Pokémon Prado",
  "tornadus_category": "Pokémon Ciclón",
  "thundurus_category": "Pokémon Rayo Golpe",
  "reshiram_category": "Pokémon Blanco Veraz",
  "zekrom_category": "Pokémon Negro Puro",
  "landorus_category": "Pokémon Abundancia",
  "kyurem_category": "Pokémon Frontera",
  "keldeo_category": "Pokémon Potro",
  "meloetta_category": "Pokémon Melodía",
  "genesect_category": "Pokémon Paleozoico",

  "chespin_category": "Pokémon Erizo",
  "quilladin_category": "Pokémon Corazaespín",
  "chesnaught_category": "Pokémon Corazaespín",
  "fennekin_category": "Pokémon Zorro",
  "braixen_category": "Pokémon Zorro",
  "delphox_category": "Pokémon Zorro",
  "froakie_category": "Pokémon Rana Burbuja",
  "frogadier_category": "Pokémon Rana Burbuja",
  "greninja_category": "Pokémon Ninja",
  "bunnelby_category": "Pokémon Excavador",
  "diggersby_category": "Pokémon Excavador",
  "fletchling_category": "Pokémon Petirrojo",
  "fletchinder_category": "Pokémon Lumbre",
  "talonflame_category": "Pokémon Flamígero",
  "scatterbug_category": "Pokémon Tiraescamas",
  "spewpa_category": "Pokémon Tiraescamas",
  "vivillon_category": "Pokémon Escamaposa",
  "litleo_category": "Pokémon Leoncito",
  "pyroar_category": "Pokémon Regio",
  "flabebe_category": "Pokémon Monoflor",
  "floette_category": "Pokémon Monoflor",
  "florges_category": "Pokémon Jardín",
  "skiddo_category": "Pokémon Montura",
  "gogoat_category": "Pokémon Montura",
  "pancham_category": "Pokémon Juguetón",
  "pangoro_category": "Pokémon Rostro Fiero",
  "furfrou_category": "Pokémon Poodle",
  "espurr_category": "Pokémon Moderación",
  "meowstic_category": "Pokémon Autocontrol",
  "honedge_category": "Pokémon Espada",
  "doublade_category": "Pokémon Espada",
  "aegislash_category": "Pokémon Espada Real",
  "spritzee_category": "Pokémon Aroma",
  "aromatisse_category": "Pokémon Fragancia",
  "swirlix_category": "Pokémon Algodoncito",
  "slurpuff_category": "Pokémon Merengue",
  "inkay_category": "Pokémon Rotación",
  "malamar_category": "Pokémon Revolución",
  "binacle_category": "Pokémon Ambidiestro",
  "barbaracle_category": "Pokémon Colectivo",
  "skrelp_category": "Pokémon Pseudoalga",
  "dragalge_category": "Pokémon Pseudoalga",
  "clauncher_category": "Pokémon Proyectagua",
  "clawitzer_category": "Pokémon Langostiro",
  "helioptile_category": "Pokémon Generador",
  "heliolisk_category": "Pokémon Generador",
  "tyrunt_category": "Pokémon Heredero",
  "tyrantrum_category": "Pokémon Tirano",
  "amaura_category": "Pokémon Tundra",
  "aurorus_category": "Pokémon Tundra",
  "sylveon_category": "Pokémon Vínculo",
  "hawlucha_category": "Pokémon Lucha Libre",
  "dedenne_category": "Pokémon Antenas",
  "carbink_category": "Pokémon Joya",
  "goomy_category": "Pokémon Suavecito",
  "sliggoo_category": "Pokémon Suavecito",
  "goodra_category": "Pokémon Dragón",
  "klefki_category": "Pokémon Llavero",
  "phantump_category": "Pokémon Tronco",
  "trevenant_category": "Pokémon Árbol Viejo",
  "pumpkaboo_category": "Pokémon Calabaza",
  "gourgeist_category": "Pokémon Calabaza",
  "bergmite_category": "Pokémon Témpano",
  "avalugg_category": "Pokémon Iceberg",
  "noibat_category": "Pokémon Onda Sónica",
  "noivern_category": "Pokémon Onda Sónica",
  "xerneas_category": "Pokémon Creación",
  "yveltal_category": "Pokémon Destrucción",
  "zygarde_category": "Pokémon Equilibrio",
  "diancie_category": "Pokémon Joya",
  "hoopa_category": "Pokémon Travesura",
  "volcanion_category": "Pokémon Vapor",
  "eternal_floette_category": "Pokémon Monoflor",

  "rowlet_category": "Pokémon Pluma Hoja",
  "dartrix_category": "Pokémon Pluma Filo",
  "decidueye_category": "Pokémon Pluma Flecha",
  "litten_category": "Pokémon Gato Fuego",
  "torracat_category": "Pokémon Gato Fuego",
  "incineroar_category": "Pokémon Rudo",
  "popplio_category": "Pokémon León Marino",
  "brionne_category": "Pokémon Fama",
  "primarina_category": "Pokémon Solista",
  "pikipek_category": "Pokémon Carpintero",
  "trumbeak_category": "Pokémon Trompeta",
  "toucannon_category": "Pokémon Cañón",
  "yungoos_category": "Pokémon Patrulla",
  "gumshoos_category": "Pokémon Vigilante",
  "grubbin_category": "Pokémon Larva",
  "charjabug_category": "Pokémon Batería",
  "vikavolt_category": "Pokémon Escarabajo",
  "crabrawler_category": "Pokémon Boxeador",
  "crabominable_category": "Pokémon Cangrejopelo",
  "oricorio_category": "Pokémon Danza",
  "cutiefly_category": "Pokémon Mosca Abeja",
  "ribombee_category": "Pokémon Mosca Abeja",
  "rockruff_category": "Pokémon Perrito",
  "lycanroc_category": "Pokémon Lobo",
  "wishiwashi_category": "Pokémon Pececito",
  "mareanie_category": "Pokémon Estrellatroz",
  "toxapex_category": "Pokémon Estrellatroz",
  "mudbray_category": "Pokémon Asno",
  "mudsdale_category": "Pokémon Caballo Tiro",
  "dewpider_category": "Pokémon Acuaburbuja",
  "araquanid_category": "Pokémon Acuaburbuja",
  "fomantis_category": "Pokémon Filo de Hoja",
  "lurantis_category": "Pokémon Filo de Flor",
  "morelull_category": "Pokémon Luminiscente",
  "shiinotic_category": "Pokémon Luminiscente",
  "salandit_category": "Pokémon Lagartoxina",
  "salazzle_category": "Pokémon Lagartoxina",
  "stufful_category": "Pokémon Rabieta",
  "bewear_category": "Pokémon Brazo Fuerte",
  "bounsweet_category": "Pokémon Fruto",
  "steenee_category": "Pokémon Fruto",
  "tsareena_category": "Pokémon Fruto",
  "comfey_category": "Pokémon Tomaflores",
  "oranguru_category": "Pokémon Sabio",
  "passimian_category": "Pokémon Cooperación",
  "wimpod_category": "Pokémon Huidizo",
  "golisopod_category": "Pokémon Blindaje",
  "sandygast_category": "Pokémon Montearena",
  "palossand_category": "Pokémon Castiarena",
  "pyukumuku_category": "Pokémon Pepino de Mar",
  "type_null_category": "Pokémon Multigénico",
  "silvally_category": "Pokémon Multigénico",
  "minior_category": "Pokémon Meteoro",
  "komala_category": "Pokémon Duermevela",
  "turtonator_category": "Pokémon Tortugabomba",
  "togedemaru_category": "Pokémon Bolita",
  "mimikyu_category": "Pokémon Disfraz",
  "bruxish_category": "Pokémon Rechinante",
  "drampa_category": "Pokémon Sosiego",
  "dhelmise_category": "Pokémon Alga Ancla",
  "jangmo_o_category": "Pokémon Escamas",
  "hakamo_o_category": "Pokémon Escamas",
  "kommo_o_category": "Pokémon Escamas",
  "tapu_koko_category": "Pokémon Espíritu Nativo",
  "tapu_lele_category": "Pokémon Espíritu Nativo",
  "tapu_bulu_category": "Pokémon Espíritu Nativo",
  "tapu_fini_category": "Pokémon Espíritu Nativo",
  "cosmog_category": "Pokémon Nebulosa",
  "cosmoem_category": "Pokémon Protostrella",
  "solgaleo_category": "Pokémon Corona Solar",
  "lunala_category": "Pokémon Corona Lunar",
  "nihilego_category": "Pokémon Parásito",
  "buzzwole_category": "Pokémon Fornido",
  "pheromosa_category": "Pokémon Elegancia",
  "xurkitree_category": "Pokémon Luminaria",
  "celesteela_category": "Pokémon Lanzamiento",
  "kartana_category": "Pokémon Desenvaine",
  "guzzlord_category": "Pokémon Tragaldabas",
  "necrozma_category": "Pokémon Prisma",
  "magearna_category": "Pokémon Artificial",
  "marshadow_category": "Pokémon Morasombra",
  "poipole_category": "Pokémon Púa Venenosa",
  "naganadel_category": "Pokémon Púa Venenosa",
  "stakataka_category": "Pokémon Muro",
  "blacephalon_category": "Pokémon Pirotecnia",
  "zeraora_category": "Pokémon Fulgor",
  "meltan_category": "Pokémon Tuerca",
  "melmetal_category": "Pokémon Tuerca",

  "grookey_category": "Pokémon Chimpancé",
  "thwackey_category": "Pokémon Ritmo",
  "rillaboom_category": "Pokémon Percusión",
  "scorbunny_category": "Pokémon Conejo",
  "raboot_category": "Pokémon Conejo",
  "cinderace_category": "Pokémon Delantero",
  "sobble_category": "Pokémon Acuartija",
  "drizzile_category": "Pokémon Acuartija",
  "inteleon_category": "Pokémon Agente",
  "skwovet_category": "Pokémon Glotón",
  "greedent_category": "Pokémon Codicioso",
  "rookidee_category": "Pokémon Pajarito",
  "corvisquire_category": "Pokémon Cuervo",
  "corviknight_category": "Pokémon Cuervo",
  "blipbug_category": "Pokémon Larva",
  "dottler_category": "Pokémon Radomo",
  "orbeetle_category": "Pokémon Siete Puntos",
  "nickit_category": "Pokémon Zorro",
  "thievul_category": "Pokémon Zorro",
  "gossifleur_category": "Pokémon Floreciente",
  "eldegoss_category": "Pokémon Adornalgodón",
  "wooloo_category": "Pokémon Borrego",
  "dubwool_category": "Pokémon Borrego",
  "chewtle_category": "Pokémon Mordelón",
  "drednaw_category": "Pokémon Mordisco",
  "yamper_category": "Pokémon Perrito",
  "boltund_category": "Pokémon Perro",
  "rolycoly_category": "Pokémon Carbón",
  "carkol_category": "Pokémon Carbón",
  "coalossal_category": "Pokémon Carbón",
  "applin_category": "Pokémon Manzanido",
  "flapple_category": "Pokémon Manzanala",
  "appletun_category": "Pokémon Manzanéctar",
  "silicobra_category": "Pokémon Serpiente Arena",
  "sandaconda_category": "Pokémon Serpiente Arena",
  "cramorant_category": "Pokémon Tragón",
  "arrokuda_category": "Pokémon Embestida",
  "barraskewda_category": "Pokémon Estaca",
  "toxel_category": "Pokémon Retoño",
  "toxtricity_category": "Pokémon Punk",
  "sizzlipede_category": "Pokémon Radiador",
  "centiskorch_category": "Pokémon Radiador",
  "clobbopus_category": "Pokémon Malcriado",
  "grapploct_category": "Pokémon Jiu-Jitsu",
  "sinistea_category": "Pokémon Té",
  "polteageist_category": "Pokémon Té",
  "hatenna_category": "Pokémon Calma",
  "hattrem_category": "Pokémon Serenidad",
  "hatterene_category": "Pokémon Silencio",
  "impidimp_category": "Pokémon Astuto",
  "morgrem_category": "Pokémon Malicioso",
  "grimmsnarl_category": "Pokémon Voluminoso",
  "obstagoon_category": "Pokémon Bloqueador",
  "perrserker_category": "Pokémon Vikingo",
  "cursola_category": "Pokémon Coral",
  "sirfetchd_category": "Pokémon Pato Salvaje",
  "mr_rime_category": "Pokémon Cómico",
  "runerigus_category": "Pokémon Recelo",
  "milcery_category": "Pokémon Crema",
  "alcremie_category": "Pokémon Crema",
  "falinks_category": "Pokémon Formación",
  "pincurchin_category": "Pokémon Erizo de Mar",
  "snom_category": "Pokémon Gusano",
  "frosmoth_category": "Pokémon Polillahielo",
  "stonjourner_category": "Pokémon Megalito",
  "eiscue_category": "Pokémon Pingüino",
  "indeedee_category": "Pokémon Emoción",
  "morpeko_category": "Pokémon Dos Caras",
  "cufant_category": "Pokémon Broncefante",
  "copperajah_category": "Pokémon Broncefante",
  "dracozolt_category": "Pokémon Fósil",
  "arctozolt_category": "Pokémon Fósil",
  "dracovish_category": "Pokémon Fósil",
  "arctovish_category": "Pokémon Fósil",
  "duraludon_category": "Pokémon Aleación",
  "dreepy_category": "Pokémon Resentido",
  "drakloak_category": "Pokémon Cuidador",
  "dragapult_category": "Pokémon Furtivo",
  "zacian_category": "Pokémon Guerrero",
  "zamazenta_category": "Pokémon Guerrero",
  "eternatus_category": "Pokémon Gigantesco",
  "kubfu_category": "Pokémon Kung-Fu",
  "urshifu_category": "Pokémon Kung-Fu",
  "zarude_category": "Pokémon Simiestro",
  "regieleki_category": "Pokémon Electrón",
  "regidrago_category": "Pokémon Dragoesfera",
  "glastrier_category": "Pokémon Corcel Feroz",
  "spectrier_category": "Pokémon Corcel Veloz",
  "calyrex_category": "Pokémon Rey",
  "wyrdeer_category": "Pokémon Gran Cuerno",
  "kleavor_category": "Pokémon Hacha",
  "ursaluna_category": "Pokémon Turba",
  "basculegion_category": "Pokémon Gran Pez",
  "sneasler_category": "Pokémon Escalada",
  "overqwil_category": "Pokémon Espinoso",
  "enamorus_category": "Pokémon Amorodio",

  "sprigatito_category": "Pokémon Gato Planta",
  "floragato_category": "Pokémon Gato Planta",
  "meowscarada_category": "Pokémon Mago",
  "fuecoco_category": "Pokémon Fuegodrilo",
  "crocalor_category": "Pokémon Fuegodrilo",
  "skeledirge_category": "Pokémon Cantante",
  "quaxly_category": "Pokémon Patito",
  "quaxwell_category": "Pokémon Disciplinado",
  "quaquaval_category": "Pokémon Bailarín",
  "lechonk_category": "Pokémon Chancho",
  "oinkologne_category": "Pokémon Chancho",
  "tarountula_category": "Pokémon Ovillo",
  "spidops_category": "Pokémon Trampa",
  "nymble_category": "Pokémon Saltamontes",
  "lokix_category": "Pokémon Saltamontes",
  "pawmi_category": "Pokémon Ratón",
  "pawmo_category": "Pokémon Ratón",
  "pawmot_category": "Pokémon Palmada",
  "tandemaus_category": "Pokémon Pareja",
  "maushold_category": "Pokémon Familia",
  "fidough_category": "Pokémon Perrito",
  "dachsbun_category": "Pokémon Perro",
  "smoliv_category": "Pokémon Aceituna",
  "dolliv_category": "Pokémon Aceituna",
  "arboliva_category": "Pokémon Aceituna",
  "squawkabilly_category": "Pokémon Loro",
  "nacli_category": "Pokémon Halita",
  "naclstack_category": "Pokémon Halita",
  "garganacl_category": "Pokémon Halita",
  "charcadet_category": "Pokémon Piroescudero",
  "armarouge_category": "Pokémon Piroguerrero",
  "ceruledge_category": "Pokémon Piroespada",
  "tadbulb_category": "Pokémon Electrocuajo",
  "bellibolt_category": "Pokémon Electrorrana",
  "wattrel_category": "Pokémon Paíño",
  "kilowattrel_category": "Pokémon Fregata",
  "maschiff_category": "Pokémon Bribón",
  "mabosstiff_category": "Pokémon Jefe",
  "shroodle_category": "Pokémon Ratón Veneno",
  "grafaiai_category": "Pokémon Mono Veneno",
  "bramblin_category": "Pokémon Estepicursor",
  "brambleghast_category": "Pokémon Estepicursor",
  "toedscool_category": "Pokémon Auricularia",
  "toedscruel_category": "Pokémon Auricularia",
  "klawf_category": "Pokémon Emboscada",
  "capsakid_category": "Pokémon Habanero",
  "scovillain_category": "Pokémon Habanero",
  "rellor_category": "Pokémon Rodante",
  "rabsca_category": "Pokémon Rodante",
  "flittle_category": "Pokémon Encaje",
  "espathra_category": "Pokémon Avestruz",
  "tinkatink_category": "Pokémon Forja",
  "tinkatuff_category": "Pokémon Martillo",
  "tinkaton_category": "Pokémon Martillo",
  "wiglett_category": "Pokémon Anguiliforme",
  "wugtrio_category": "Pokémon Anguiliforme",
  "bombirdier_category": "Pokémon Arrojador",
  "finizen_category": "Pokémon Delfín",
  "palafin_category": "Pokémon Delfín",
  "varoom_category": "Pokémon Monocilindro",
  "revavroom_category": "Pokémon Policilindro",
  "cyclizar_category": "Pokémon Montura",
  "orthworm_category": "Pokémon Lombriz",
  "glimmet_category": "Pokémon Mineral",
  "glimmora_category": "Pokémon Mineral",
  "greavard_category": "Pokémon Can Fantasma",
  "houndstone_category": "Pokémon Can Fantasma",
  "flamigo_category": "Pokémon Sincronizado",
  "cetoddle_category": "Pokémon Geoballena",
  "cetitan_category": "Pokémon Geoballena",
  "veluza_category": "Pokémon Sueltalastre",
  "dondozo_category": "Pokémon Gran Bagre",
  "tatsugiri_category": "Pokémon Mimetismo",
  "annihilape_category": "Pokémon Mono Furia",
  "clodsire_category": "Pokémon Pez Púas",
  "farigiraf_category": "Pokémon Gran Cuello",
  "dudunsparce_category": "Pokémon Serpiente Tierra",
  "kingambit_category": "Pokémon Gran Espada",
  "great_tusk_category": "Pokémon Paradoja",
  "scream_tail_category": "Pokémon Paradoja",
  "brute_bonnet_category": "Pokémon Paradoja",
  "flutter_mane_category": "Pokémon Paradoja",
  "slither_wing_category": "Pokémon Paradoja",
  "sandy_shocks_category": "Pokémon Paradoja",
  "iron_treads_category": "Pokémon Paradoja",
  "iron_bundle_category": "Pokémon Paradoja",
  "iron_hands_category": "Pokémon Paradoja",
  "iron_jugulis_category": "Pokémon Paradoja",
  "iron_moth_category": "Pokémon Paradoja",
  "iron_thorns_category": "Pokémon Paradoja",
  "frigibax_category": "Pokémon Aleta Hielo",
  "arctibax_category": "Pokémon Aleta Hielo",
  "baxcalibur_category": "Pokémon Dragón Hielo",
  "gholdengo_category": "Pokémon Tesoro",
  "wo_chien_category": "Pokémon Debacle",
  "chien_pao_category": "Pokémon Debacle",
  "ting_lu_category": "Pokémon Debacle",
  "chi_yu_category": "Pokémon Debacle",
  "roaring_moon_category": "Pokémon Paradoja",
  "iron_valiant_category": "Pokémon Paradoja",
  "koraidon_category": "Pokémon Paradoja",
  "miraidon_category": "Pokémon Paradoja",
  "walking_wake_category": "Pokémon Paradoja",
  "iron_leaves_category": "Pokémon Paradoja",
  "archaludon_category": "Pokémon Aleación",
  "gouging_fire_category": "Pokémon Paradoja",
  "raging_bolt_category": "Pokémon Paradoja",
  "iron_boulder_category": "Pokémon Paradoja",
  "iron_crown_category": "Pokémon Paradoja",
  "bloodmoon_ursaluna_category": "Pokémon Turba",

  "alola_rattata_category": "Pokémon Ratón",
  "alola_raticate_category": "Pokémon Ratón",
  "alola_raichu_category": "Pokémon Ratón",
  "alola_sandshrew_category": "Pokémon Ratón",
  "alola_sandslash_category": "Pokémon Ratón",
  "alola_vulpix_category": "Pokémon Zorro",
  "alola_ninetales_category": "Pokémon Zorro",
  "alola_diglett_category": "Pokémon Topo",
  "alola_dugtrio_category": "Pokémon Topo",
  "alola_meowth_category": "Pokémon Gato Arañazo",
  "alola_persian_category": "Pokémon Sofistigato",
  "alola_geodude_category": "Pokémon Roca",
  "alola_graveler_category": "Pokémon Roca",
  "alola_golem_category": "Pokémon Megatón",
  "alola_grimer_category": "Pokémon Lodo",
  "alola_muk_category": "Pokémon Lodo",
  "alola_exeggutor_category": "Pokémon Coco",
  "alola_marowak_category": "Pokémon Apilahueso",

  "galar_meowth_category": "Pokémon Gato Arañazo",
  "galar_ponyta_category": "Pokémon Unicuerno",
  "galar_rapidash_category": "Pokémon Unicuerno",
  "galar_slowpoke_category": "Pokémon Atontado",
  "galar_slowbro_category": "Pokémon Ermitaño",
  "galar_farfetchd_category": "Pokémon Pato Salvaje",
  "galar_weezing_category": "Pokémon Gas Venenoso",
  "galar_mr_mime_category": "Pokémon Danza",
  "galar_articuno_category": "Pokémon Cruel",
  "galar_zapdos_category": "Pokémon Patas Recias",
  "galar_moltres_category": "Pokémon Malignidad",
  "galar_slowking_category": "Pokémon Regio",
  "galar_corsola_category": "Pokémon Coral",
  "galar_zigzagoon_category": "Pokémon Mapachito",
  "galar_linoone_category": "Pokémon Lanzado",
  "galar_darumaka_category": "Pokémon Daruma",
  "galar_darmanitan_category": "Pokémon Daruma",
  "galar_yamask_category": "Pokémon Espíritu",
  "galar_stunfisk_category": "Pokémon Trampa",

  "hisui_growlithe_category": "Pokémon Explorador",
  "hisui_arcanine_category": "Pokémon Leyenda",
  "hisui_voltorb_category": "Pokémon Esfera",
  "hisui_electrode_category": "Pokémon Esfera",
  "hisui_typhlosion_category": "Pokémon Fuego Fatuo",
  "hisui_qwilfish_category": "Pokémon Globo",
  "hisui_sneasel_category": "Pokémon Garra Filo",
  "hisui_samurott_category": "Pokémon Majestuoso",
  "hisui_lilligant_category": "Pokémon Pirueta",
  "hisui_zorua_category": "Pokémon Zorro Rencor",
  "hisui_zoroark_category": "Pokémon Maldizorro",
  "hisui_braviary_category": "Pokémon Grito Guerra",
  "hisui_sliggoo_category": "Pokémon Caracol",
  "hisui_goodra_category": "Pokémon Retracción",
  "hisui_avalugg_category": "Pokémon Iceberg",
  "hisui_decidueye_category": "Pokémon Pluma Flecha",

  "paldea_tauros_category": "Pokémon Toro Bravo",
  "paldea_wooper_category": "Pokémon Pez Veneno"
}
