{
  "trappedDesc": "bị bẫy",
  "flinchedDesc": "bị doạ",
  "confusedDesc": "rối loạn",
  "infatuatedDesc": "mê muội",
  "seedDesc": "nhiễm hạt",
  "nightmareDesc": "ác mộng",
  "ingrainDesc": "cắm rễ",
  "drowsyDesc": "buồn ngủ",
  "rechargingLapse": "{{pokemonNameWithAffix}} phải\nchờ hồi phục!",
  "trappedOnAdd": "{{pokemonNameWithAffix}} không thể \ntrốn thoát!",
  "trappedOnRemove": "{{pokemonNameWithAffix}} được giải thoát\nkhỏi {{moveName}}!",
  "flinchedLapse": "{{pokemonNameWithAffix}} bị doạ!",
  "confusedOnAdd": "{{pokemonNameWithAffix}} trở lên\nrối loạn!",
  "confusedOnRemove": "{{pokemonNameWithAffix}} thoát khỏi\nsự rối loạn!",
  "confusedOnOverlap": "{{pokemonNameWithAffix}} đang\nbị rối loạn rồi!",
  "confusedLapse": "{{pokemonNameWithAffix}} bị\nrối loạn!",
  "confusedLapseHurtItself": "Tự làm bản thân bị thương\nkhi đang rối loạn!",
  "destinyBondLapseIsBoss": "{{pokemonNameWithAffix}} không bị ảnh hưởng\nbởi hiệu ứng của Destiny Bond.",
  "destinyBondLapse": "{{pokemonNameWithAffix}} kéo\n{{pokemonNameWithAffix2}} xuống mồ cùng mình!",
  "laserFocusOnAdd": "{{pokemonNameWithAffix}} tập trung hoàn toàn!",
  "healBlockOnAdd": "{{pokemonNameWithAffix}} bị chống phục hồi HP!",
  "healBlockOnRemove": "{{pokemonNameWithAffix}} không còn\nbị chống hồi phục HP!",
  "healBlockCannotHeal": "{{pokemonNameWithAffix}} bị chống phục hồi HP!",
  "infatuatedOnAdd": "{{pokemonNameWithAffix}} rơi vào lưới tình\nvới {{sourcePokemonName}}!",
  "infatuatedOnOverlap": "{{pokemonNameWithAffix}} đang\nmê muội trong lưới tình!",
  "infatuatedLapse": "{{pokemonNameWithAffix}} rơi vào tình yêu\nvới {{sourcePokemonName}}!",
  "infatuatedLapseImmobilize": "{{pokemonNameWithAffix}} bị\ntình yêu che mắt!",
  "infatuatedOnRemove": "{{pokemonNameWithAffix}} đã vượt qua\nmê muội.",
  "seededOnAdd": "{{pokemonNameWithAffix}} bị nhiễm hạt!",
  "seededLapse": "{{pokemonNameWithAffix}}’s máu bị\nhút đi bởi Leech Seed!",
  "seededLapseShed": "{{pokemonNameWithAffix}}’s Leech Seed\nhút hết dịch lỏng!",
  "nightmareOnAdd": "{{pokemonNameWithAffix}} bắt đầu\nthấy ác mộng sống dậy!",
  "nightmareOnOverlap": "{{pokemonNameWithAffix}} bị\nác mộng làm sợ hãi!",
  "nightmareLapse": "{{pokemonNameWithAffix}} bị khống chế\ntrong ác mộng!",
  "encoreOnAdd": "{{pokemonNameWithAffix}} được\ncổ vũ bởi Encore!",
  "encoreOnRemove": "{{pokemonNameWithAffix}}’s cổ vũ của Encore\nkết thúc!",
  "helpingHandOnAdd": "{{pokemonNameWithAffix}} sẵn sàng\ngiúp đỡ {{pokemonName}}!",
  "ingrainLapse": "{{pokemonNameWithAffix}} hấp thụ\ndưỡng chất nhờ cắm rễ!",
  "ingrainOnTrap": "{{pokemonNameWithAffix}} bắt đầu cắm rễ!",
  "aquaRingOnAdd": "{{pokemonNameWithAffix}} bao quanh\nbản thân bằng thủy lực!",
  "aquaRingLapse": "{{moveName}} hồi lại\n{{pokemonName}}’s HP!",
  "drowsyOnAdd": "{{pokemonNameWithAffix}} cảm thấy buồn ngủ!",
  "damagingTrapLapse": "{{pokemonNameWithAffix}} bị thương\nbởi {{moveName}}!",
  "bindOnTrap": "{{pokemonNameWithAffix}} bị ép chặt bởi\n{{sourcePokemonName}}’s {{moveName}}!",
  "wrapOnTrap": "{{pokemonNameWithAffix}} đang bị kẹp chặt\nbởi {{sourcePokemonName}}!",
  "vortexOnTrap": "{{pokemonNameWithAffix}} bị kẹt\ntrong xoáy nước!",
  "clampOnTrap": "{{sourcePokemonNameWithAffix}} Kẹp chặt\n{{pokemonName}}!",
  "sandTombOnTrap": "{{pokemonNameWithAffix}} bị kẹt lại\nbởi {{moveName}}!",
  "magmaStormOnTrap": "{{pokemonNameWithAffix}} bị bẫy trong\nmagma nóng bỏng!",
  "snapTrapOnTrap": "{{pokemonNameWithAffix}} kẹt bẫy\nbởi snap trap!",
  "thunderCageOnTrap": "{{sourcePokemonNameWithAffix}} bẫy\n{{pokemonNameWithAffix}}!",
  "infestationOnTrap": "{{pokemonNameWithAffix}} bị nhiễm phải\nlây nhiễm bọ bởi {{sourcePokemonNameWithAffix}}!",
  "protectedOnAdd": "{{pokemonNameWithAffix}}\ntự bảo vệ lấy bản thân!",
  "protectedLapse": "{{pokemonNameWithAffix}}\ntự bảo vệ!",
  "enduringOnAdd": "{{pokemonNameWithAffix}} chuẩn bị\nbản thân trước đòn đánh!",
  "enduringLapse": "{{pokemonNameWithAffix}} chịu đựng\nđược đòn đánh!",
  "sturdyLapse": "{{pokemonNameWithAffix}} chịu đựng\nlấy đòn đánh!",
  "perishSongLapse": "{{pokemonNameWithAffix}}’s lượt đếm tử vong chỉ còn {{turnCount}}.",
  "centerOfAttentionOnAdd": "{{pokemonNameWithAffix}} trở thành trung tâm\ncủa mọi đòn đánh!",
  "truantLapse": "{{pokemonNameWithAffix}} nằm\nnghỉ hết lượt!",
  "slowStartOnAdd": "{{pokemonNameWithAffix}} không\nthể bắt đầu ngay!",
  "slowStartOnRemove": "{{pokemonNameWithAffix}} cuối cùng\ncũng đã sẵn sàng chiến đấu!",
  "highestStatBoostOnAdd": "{{pokemonNameWithAffix}}’s {{statName}}\nđược cường hoá!",
  "highestStatBoostOnRemove": "Hiệu ứng của {{pokemonNameWithAffix}}’s\n{{abilityName}} đã hết tác dụng!",
  "magnetRisenOnAdd": "{{pokemonNameWithAffix}} bắt đầu lở lửng nhờ lực điện từ !",
  "magnetRisenOnRemove": "{{pokemonNameWithAffix}}’s lực điện từ trên sân đã hết tác dụng!",
  "critBoostOnAdd": "{{pokemonNameWithAffix}} đang thấy\nhăng chiến!",
  "critBoostOnRemove": "{{pokemonNameWithAffix}} cảm thấy bình tĩnh.",
  "saltCuredOnAdd": "{{pokemonNameWithAffix}} đang bị ướp muối!",
  "saltCuredLapse": "{{pokemonNameWithAffix}} bị thương bởi {{moveName}}!",
  "cursedOnAdd": "{{pokemonNameWithAffix}} tự hi sinh một nửa HP và đặt lời nguyền lên {{pokemonName}}!",
  "cursedLapse": "{{pokemonNameWithAffix}} bị ảnh hưởng bởi Curse!",
  "stockpilingOnAdd": "{{pokemonNameWithAffix}} bắt đầu tích trữ {{stockpiledCount}}!",
  "disabledOnAdd": "{{pokemonNameWithAffix}}’s {{moveName}}\nbị vô hiệu hoá!",
  "disabledOnRemove": "{{pokemonNameWithAffix}}’s {{moveName}}\nkhông còn bị vô hiệu hoá!",
  "tarShotOnAdd": "{{pokemonNameWithAffix}} trở nên yếu hơn với hệ Lửa!",
  "shedTailOnAdd": "{{pokemonNameWithAffix}} bỏ lại đuôi mình và tạo ra 1 mồi nhử!",
  "substituteOnAdd": "{{pokemonNameWithAffix}} tạo nhanh 1 con rối thay thế!",
  "substituteOnHit": "Con rối thay thế nhận lấy sát thương {{pokemonNameWithAffix}}!",
  "substituteOnRemove": "{{pokemonNameWithAffix}}’s con rối thay thế biến mất!",
  "tormentOnAdd": "{{pokemonNameWithAffix}} bị đẩy vào giày vò!",
  "tauntOnAdd": "{{pokemonNameWithAffix}} bị khiêu khích!",
  "tauntOnRemove": "{{pokemonNameWithAffix}} mặc kệ khiêu khích!",
  "imprisonOnAdd": "{{pokemonNameWithAffix}} khoá hết chiêu thức\nmà mục tiêu cùng sở hữu!",
  "autotomizeOnAdd": "{{pokemonNameWithAffix}} trở lên nhanh nhẹn hơn!",
  "syrupBombOnAdd": "{{pokemonNameWithAffix}} tự bao trùm bản thân trong siro kẹo!",
  "syrupBombLapse": "Siro kẹo đang làm chậm {{pokemonNameWithAffix}}!",
  "telekinesisOnAdd": "{{pokemonNameWithAffix}} bị hất lên trời!",
  "telekinesisOnRemove": "{{pokemonNameWithAffix}} đã giải thoát khỏi thần kinh lực!",
  "electrifiedOnAdd": "{{pokemonNameWithAffix}}’s các chiêu thức đã được nhiễm điện hoá!",
  "powerTrickActive": "{{pokemonNameWithAffix}} đổi chỉ số Attack và Defense!",
  "powderOnAdd": "{{pokemonNameWithAffix}} được bao trùm bởi bột nổ!",
  "powderLapse": "Khi có lửa chạm vào\nPokémon dính bột, nó sẽ phát nổ tung ngay!",
  "grudgeOnAdd": "{{pokemonNameWithAffix}} muốn mục tiêu mang hận thù!",
  "grudgeLapse": "{{pokemonNameWithAffix}} mất hết {{moveName}}’s NL bởi mối hận của mình!",
  "magicCoatOnAdd": "{{pokemonNameWithAffix}} tự bao quanh bản thân nhờ Magic Coat!",
  "supremeOverlordOnAdd": "{{pokemonNameWithAffix}} nhận lấy sức mạnh tình bạn từ các đồng minh đã mất khả năng chiến đấu!"
}
