{
  "stench": {
    "name": "Kiratsa"
  },
  "drizzle": {
    "name": "Zirimiri"
  },
  "speedBoost": {
    "name": "Bizkortzea"
  },
  "battleArmor": {
    "name": "Borroka Armadura",
    "description": "Bere armadura gogorrak kolpe kritikoetatik babesten du."
  },
  "sturdy": {
    "name": "Mardultasuna"
  },
  "damp": {
    "name": "Hezetasuna"
  },
  "limber": {
    "name": "Malgutasuna",
    "description": "Pokémon honen gorputz malguak paralisia ekiditzen du."
  },
  "sandVeil": {
    "name": "Hare Estalkia"
  },
  "static": {
    "name": "Elekt. Estatikoa"
  },
  "voltAbsorb": {
    "name": "Tentsio Xurgaketa"
  },
  "waterAbsorb": {
    "name": "Ur Xurgaketa"
  },
  "oblivious": {
    "name": "Despistatua"
  }
}
