{
  "battlesWon": "{{count, number}} 판 승리했어요!",
  "underratedPokemon": "과소평가된 포켓몬: {{pokemonName}}!",
  "joinTheDiscord": "디스코드에 가입하세요!",
  "infiniteLevels": "무한한 레벨!",
  "everythingIsStackable": "모두 중첩 가능!",
  "optionalSaveScumming": "원한다면 세이브 노가다를!",
  "biomes": "38개의 지역!",
  "playWithSpeed": "5배속으로 플레이해봐요!",
  "liveBugTesting": "라이브 버그 테스트!",
  "heavyInfluence": "RoR2에 강하게 영감을 받았어요!",
  "pokemonRiskAndPokemonRain": "포켓몬 '리스크' 오브 포켓몬 '레인'!",
  "nowWithMoreSalt": "이제 33% 더 과몰입 가능!",
  "infiniteFusionAtHome": "집에서 인피니트 퓨전을 즐겨보세요!",
  "brokenEggMoves": "알기술까기!",
  "magnificent": "고무적이군",
  "doPeopleReadThis": "여기 떠 있는 거 읽어요?",
  "thatsCrazy": "미쳤습니다!",
  "gottaCatchEmAll": "포켓몬 넌 내 꺼야!",
  "questionableBalancing": "의심스러운 밸런싱!",
  "coolShaders": "쿨한 셰이더!",
  "aiFree": "AI 없음!",
  "suddenDifficultySpikes": "돌연사 가능!",
  "basedOnAnUnfinishedFlashGame": "무한 플래시게임 기반!",
  "moreAddictiveThanIntended": "기획보다 중독적이에요!",
  "mostlyConsistentSeeds": "일관성있는 랜덤 시드!",
  "achievementPointsDontDoAnything": "업적 포인트는 아무것도 하지 않습니다!",
  "nothingBeatsAJellyFilledDonut": "국밥보다 든든한 건 없지!",
  "dontTalkAboutThePokemonIncident": "{{pokemonName}} 사건에 대해선 이야기하지 맙시다!",
  "alsoTryPokengine": "Pokéngine도 해 보세요!",
  "alsoTryEmeraldRogue": "Emerald Rogue도 해 보세요!",
  "alsoTryRadicalRed": "Radical Red도 해 보세요!",
  "eeveeExpo": "이브이 엑스포!",
  "checkOutYnoproject": "YNOproject에 접속해 보세요!",
  "breedersInSpace": "충격!우주에 브리더 진짜 계심ㄷㄷ",
  "alsoTryPokemonUnbound": "Pokemon Unbound도 해 보세요!",
  "tryTheJohtoDragonChallenge": "2세대 드래곤 타입 챌린지에 도전해보세요!",
  "basicReadingAbilityRecommended": "기초적인 독해 능력 권장됨!",
  "shoutoutsToTheArtists": "아티스트분들께 샤라웃~!",
  "gamblingNotEncouraged": "도박은 추천하지 않아요!",
  "dontForgetToTakeABreak": "쉬엄쉬엄 하세요!",
  "wEvent": "W 이벤트",
  "ifItsNotAccurateItsAccurate": "100% 명중률이 아니라면 사실상 50%",
  "everyLossIsProgressMade": "나를 죽이지 못하는 것은 나를 더 강하게 만든다!",
  "liveWoChienReaction": "실시간 총지엔 반응:",
  "itsAFeatureNotABug": "버그가 아니라 기능이에요",
  "theEggsAreNotForEating": "알은 먹으면 안 돼요!",
  "7.8outOf10TooManyWaterBiomes": "7.8/10, 물 바이옴이 너무 많음.",
  "butNothingHappened": "그러나 아무 일도 일어나지 않았다!",
  "thePowerOfScienceIsAmazing": "과학의 힘이란 대단해~!",
  "freeToPlay": "무과금 게임",
  "theresATimeAndPlaceForEverything": "세상 모든 일에는 때와 장소가 있는 법이죠!",
  "nowWithShinierShinies": "원래와 색이 다른 포켓몬을 만나보세요!",
  "smilesGoForMiles": "모두 웃는 얼굴로 밝은 길드를 만들자!",
  "certainlyNotDragonFree": "확실히 드래곤 포켓몬은 만만하지 않네요!",
  "haveANiceDay": "좋은 하루 되세요!",
  "redacted": "[REDACTED]",
  "hi": "안녕",
  "transRights": "정치적 올바름!",
  "shinyOddsHigherThanYouThink": "생각 보다 높은 색이 다른 포켓몬 확률!",
  "noFalseTrades": "가짜 트레이드 없음!",
  "notForProfit": "비영리 게임이에요!",
  "timeForYourDailyRun": "데일리 런 할 시간!",
  "moreEggsThanADaycare": "키우미집보다 알 많이 줌!",
  "disclaimerHarshSunDoesNotGiveVitaminD": "면책사항: 햇살이 강해져도 비타민D는 나오지 않아요!",
  "whoNeedsAMap": "지도 필요하신 분?",
  "luxrayIsNotADarkType": "렌트라는 악 타입 아님!",
  "selfDestructiveEncounters": "습기 없이 자폭 맞기!",
  "mostOptionsAreViable": "대부분 옵션으로 커버 가능!",
  "pokerogueMorse": ".--. --- -.- . .-. --- --. ..- .",
  "smiley": ":)",
  "beAwareOfPassives": "항상 패시브를 조심하세요!",
  "asSeenOnTheWorldWideWeb": "전 세계에서 플레이 중!",
  "vaultinVeluzas": "우옷! 우오오옷!",
  "tooManyStarters": "스타팅 포켓몬이 한가득!",
  "checkTheWiki": "위키 참조!",
  "winWithYourFavorites": "최애 포켓몬과 함께 승리해보세요!",
  "alsoTryPokerogueWait": "포켓로그도 해 보세요! …응?!",
  "theWayISeeItKyogreIsSurrounded": "내가 보기에, 가이오가는 둘러싸여 있어요…",
  "tryOutHoneyGather": "꿀모으기 특성을 활용해보세요!",
  "notForTheFaintOfHeart": "심신미약자에게 권장되지 않음!",
  "p": "(P)",
  "flipYourDeviceToEvolveInkay": "사용 중인 기기를 뒤집어 오케이징을 진화시켜 보세요!",
  "inArceusWeTrust": "아르세우스님 믿쑵니다",
  "whyDidTheTorchicCrossTheRoad": "아차모가 왜 길건너 친구들을 하고 있나요?",
  "goodLuck": "행운을 빌어요!",
  "fuseWisely": "융합은 신중하게!",
  "compensation": "점검 보상?",
  "prepareForTroubleAndMakeItDouble": "누구냐? 라고 물으신다면! 대답해 드리는 게 인지상정!",
  "anEggForYourTroubles": "보상으로 알을 드립니다!",
  "regirock": "ÜN ÜN ÜN",
  "hereForAGoodTime": "좋은 시간 되세요!",
  "getGoodOrDont": "잘 좀 해봐! 아님 말고",
  "checkTheSubreddit": "레딧을 확인해보세요!",
  "betterNerfGreninja": "개굴닌자 너프 좀!",
  "inCaseOfUpdateClearYourCache": "업데이트 이후 웹 캐시를 삭제하세요!",
  "insertTextHere": "여기에 텍스트 입력",
  "endingEndlessNotFound": "ending_endless를 찾을 수 없습니다.",
  "iLikeMyEggsVouchered": "난 알 바우처가 좋아!",
  "YOU": "너!",
  "noAddedSugar": "무가당!",
  "notSponsored": "스폰서 없음!",
  "notRated": "평점 없음!",
  "justOneMoreWaveMom": "엄마, 한 웨이브만 더요!",
  "saltCured": "소금에 절여졌다!",
  "onlyOnPokerogueNet": "pokerogue.net에서만!",
  "pixelPerfection": "완벽한 도트 그래픽!",
  "openSource": "오픈소스!",
  "probablyGood": "아마 재밌을걸?",
  "itsAMonsterHouse": "포켓몬 소굴이다!",
  "dontForgetYourPassword": "비밀번호 까먹지 마세요!",
  "tripleTripleTripleAxel": "트리플-트리플-트리플 악셀!",
  "questionExclamation": "?!",
  "clownEncounters": "어릿광대 조우!",
  "fullOfBerries": "나무열매가 가득!",
  "limitsAreMeantToBeBrokenSometimes": "한계는 돌파하라고 있는거죠! 가끔이지만…",
  "keepItCasual": "가볍게 즐기세요!",
  "serversProbablyWorking": "아마 서버 가동 중!",
  "mew": "아마 트럭 밑에 뮤가 없는 듯!",
  "makeItRainAndYourProblemsGoAway": "골드러시로 문제 해결!",
  "customMusicTracks": "커스텀 음악 트랙!",
  "youAreValid": "당신은 소중한 사람이에요!",
  "number591IsLookingOff": "도감번호 591번을 자세히 보면…",
  "timeForYourDeliDelivery": "딜리버-디의 선물이 도착했어요!",
  "goodFirstImpression": "우리의 첫인상이 호감이었길 바라요!",
  "iPreferRarerCandies": "난 더이상한사탕이 좋아!",
  "pocketRoguelite": "포켓로걸라이트!",
  "porygonDidNothingWrong": "폴리곤은 아무 잘못도 하지 않았어요!",
  "critMattered": "급소를 노리자!",
  "pickupNotRequired": "픽업은 필수가 아닌 선택!",
  "stayHydrated": "수분을 유지하도록 해요!",
  "alsoTryCobblemon": "Cobblemon도 해 보세요!",
  "alsoTryPokeDoku": "PokeDoku도 해 보세요!",
  "mySleepStyleIsDoesnt": "나의 수면 타입은 '자지않는타입'",
  "makeYourOwnWorldChampDifference": "나만의 World Champ Difference를 만들어 보세요!",
  "yoChampInTheMaking": "어-이! 미래의 챔피언!",
  "notLiableForDecisionAnxiety": "결정 불안에 대한 책임을 지지 않습니다!",
  "theAirIsTastyHere": "이 동네 공기 죽음으로 맛있는데!",
  "continue": "계속 하시겠습니까?",
  "startANewRunToday": "오늘의 새로운 런을 시작해봐요!",
  "neverGiveUp": "절대 포기하지 마!",
  "theresAlwaysNextTime": "위기는 기회의 또 다른 이름!",
  "oneTwoThreeAndPoof": "하나, 둘… 퍼엉!",
  "yourPokemonOnlyGoToLevelOneHundred": "포켓몬의 만렙이 100이라고 생각했나요?",
  "theBattlesWillBeLegendary": "이 배틀은 전설이 될거에요!",
  "levelCurveBetterThanJohto": "성도 지방보다 나은 레벨 디자인!",
  "alsoTryShowering": "Showering도 해 보세요!",
  "wellStillBeHere": "언제든 돌아올 수 있도록 여기에서 기다릴게요!",
  "weHopeToSeeYouAgain": "꼭 다시 봐요!",
  "aHealthyTeamCanMeanGreaterRewards": "건강한 팀은 더 큰 실적이 됩니다!",
  "aWildPokemonAppeared": "앗! 야생 {{pokemonName}}[[가]] 튀어나왔다!",
  "isThisThingOn": "이거 켜져 있나요?",
  "needsMoreTesting": "테스트가 더 필요해요!",
  "whoChecksStatChanges": "스탯 변경 확인해본 사람?",
  "whenTwoTrainersEyesMeet": "눈과 눈이 마주치면 포켓몬 승부!",
  "notOfficiallyOnSteam": "Steam에 있는 건 공식이 아닙니다!",
  "fiftyFifty": "시작이 반이고, 가만히 있으면 반을 가니까…",
  "metaNotIncluded": "메타 미포함!",
  "bornToBeAWinner": "난 태어났을 때부터 져본 적이 없어!",
  "onARollout": "출시 중!",
  "itsAlwaysNightDeepInTheAbyss": "심연은 항상 밤이에요!",
  "folksThisIsInsane": "말이 안 되는 거잖아!!",
  "newYears": {
    "happyNewYear": "새해 복 많이 받으세요!",
    "andAHappyNewYear": "그리고… 새해 복 많이 받으세요!"
  },
  "valentines": {
    "happyValentines": "해피 발렌타인!",
    "fullOfLove": "사랑을 담아서!",
    "applinForYou": "과사삭벌레 하나 줄까요?",
    "thePowerOfLoveIsThreeThirtyBST": "사랑의 힘은 종족값이 330이랍니다!",
    "haveAHeartScale": "여기 하트비늘이요!",
    "i<3You": "<3해!"
  },
  "aprilFools": {
    "battlesOne": ">1 판 승리했어요!",
    "aprilFools": "만우절!!",
    "removedPokemon": "{{pokemonName}}[[가]] 삭제되었습니다!",
    "helloKyleAmber": "안녕! {{name}}.",
    "gotcha": "넌 내꺼야!",
    "alsoTryPokerogueTwo": "포켓로그2도 해 보세요!",
    "nowWithSameScumCountermeasures": "세이브파일 변조 방지 기술이 구현되었어요!",
    "neverGonnaGiveYouGoodRolls": "이제 좋은 거 절대 안 나옵니다 ㅋㅋ",
    "youBumblingBuffoon": "이 바보 멍청이!",
    "doubleShinyOddsForTrainersOnly": "색이 다른 포켓몬 확률 2배… 너만 빼고!",
    "nowWithZMoves": "Z기술이 구현되었어요!",
    "newLightType": "신규 타입: 빛 타입!",
    "removedMegas": "메가진화가 삭제되었습니다!",
    "nerfedYourFavorites": "당신이 좋아하는 포켓몬을 너프했어요!",
    "grrr": "왈왈! 왈왈!! 으르르 크르르릉!!!",
    "enabledEternatusPassiveGoodLuck": "무한다이노의 패시브를 비활성화 했어요! 행운을 빌어요!",
    "theDarkestDaySoundsLikeAFutureProblem": "가장 어두운 게 뭔지 아세요? 눈을 감으면 알 수 있을 거에요!",
    "tmShopWhen": "기술머신 상점 언제 나옴?",
    "whoIsFinn": "핀이… 누구더라?",
    "watchOutForShadowPokemon": "쉐도우 포켓몬을 찾아봐요!",
    "nowWithDarkTypeLuxray": "렌트라에 악타입이 추가됐어요!",
    "didYouKnow": "그거 알아?",
    "onlyOnPokerogueNetAGAIN": "오직 POKEROGUE.NET만!",
    "noFreeVouchers": "바우처는 이제 없어요! 포켓몬은 직접 파밍하세요!",
    "altffourAchievementPoints": "Alt + F4를 누르면 업적 상점이 열려요!",
    "areYouPiratingThis": "이거 불법 복제하시나요? 왜요?",
    "rokePogue": "로켓포그!",
    "readMe": "READ ME!",
    "winningNotIncluded": "승리 미포함!",
    "timeForYourSoloUnownRun": "안농 런을 할 시간이에요!",
    "nowARealTimeStrategyGame": "이제 RTS 게임입니다!",
    "nowWithQuickTimeEncounters": "이제 QTE가 가능합니다!",
    "timeYourInputsForHigherCatchrate": "더 높은 포획률을 위해 시간을 투자하세요!",
    "certifiedButtonSimulator": "검증된 Z키 시뮬레이터!",
    "iHopeYouGetSuckerPunched": "당신이 기습을 맞았으면 좋겠네요!"
  },
  "halloween": {
    "happyHalloween": "해피 할로윈!",
    "boo": "부-!",
    "pumpkabooAbout": "호바귀는 스탯에 따라 사이즈가 달라져요!",
    "mayContainSpiders": "거미 출몰 주의!",
    "spookyScarySkeledirge": "으스스하고 무서운 라우드본!",
    "gourgeistUsedTrickOrTreat": "펌킨인의 핼러윈!",
    "letsSnuggleForever": "투닥투닥프렌드타임!"
  },
  "winterHoliday": {
    "happyHolidays": "메리-프 크리스마스!",
    "delibirdSeason": "딜리버드의 계절!",
    "unaffilicatedWithDelibirdServices": "딜리버드 배달부는 단순변심 등의 사유로 반품/환불은 받지 않습니다!",
    "diamondsFromTheSky": "다이아몬드 더스트가 내려요!",
    "holidayStylePikachuNotIncluded": "피카츄가 크리스마스 옷으로는 갈아입기 싫다네요!",
    "delibirdDirectlyToYourHouse": "딜리버드가 당신의 집으로 찾아갑니다!",
    "haveAnIceDay": "조흔 하루 되세요!",
    "spinTheClaydol": "돌고 도는 점토도리!",
    "beGoodForGoodnessSake": "좋은 사람이 되세요, 그것이 바로 좋은 일이니까요!",
    "moomooMilkAndLavaCookies": "튼튼밀크와 용암전병!",
    "iNeedAYacheBerry": "플카열매가 필요해…",
    "getJolly": "명랑 성격을 얻어봐요!",
    "tisTheSeasonToBeSpeSpa": "스피드가 오르고 특공이 내려가는 시즌이네요!",
    "deckTheHalls": "홀을 장식해봐요!",
    "saveScummingGetsYouOnTheNaughtyList": "세이브파일 변조하면 나쁜아이 목록에 올라갈거에요!",
    "badTrainersGetRolycoly": "나쁜 트레이너는 탄동을 얻게 될거에요!"
  }
}
