{
  "battlesWon": "勝ったバトル：{{count, number}}回！",
  "joinTheDiscord": "Discordにも入ってね！",
  "infiniteLevels": "レベルは無限大！",
  "everythingIsStackable": "全部スタックできる！",
  "optionalSaveScumming": "リセマラをご自由に！",
  "biomes": "バイオーム　３８つ！",
  "playWithSpeed": "５x 速さでプレイしてみて！",
  "liveBugTesting": "生バグフィックス！",
  "heavyInfluence": "Risk of Rain 2の影響がでかい！",
  "pokemonRiskAndPokemonRain": "ポケットモンスター リスク & ポケットモンスター レイン！",
  "nowWithMoreSalt": "イライラ保証付き！",
  "infiniteFusionAtHome": "インフィニットフュージョン低品質版！",
  "brokenEggMoves": "OPすぎるタマゴ技！",
  "magnificent": "お見事でございます！",
  "doPeopleReadThis": "誰がこれを読むんだろう？",
  "thatsCrazy": "そんな無茶な！",
  "gottaCatchEmAll": "ポケモンゲットだぜ！",
  "questionableBalancing": "ゲームバランスは怪しいかも！",
  "coolShaders": "かっこいいシェーダー！",
  "aiFree": "AIナシ！",
  "suddenDifficultySpikes": "いきなり難しくなる！",
  "basedOnAnUnfinishedFlashGame": "基礎は未完成なフラッシュゲーム！",
  "moreAddictiveThanIntended": "ハマりすぎるかも！",
  "mostlyConsistentSeeds": "ほとんど一貫しているシード！",
  "achievementPointsDontDoAnything": "実績ポイントは意味ないです！",
  "nothingBeatsAJellyFilledDonut": "丸いのは梅干し三角のはコンブだぞ！",
  "dontTalkAboutTheTinkatonIncident": "デカヌチャン事変は持ち出さないように！",
  "alsoTryPokengine": "Pokéngineも試してね！",
  "alsoTryEmeraldRogue": "Emerald Rogueも試してね！",
  "alsoTryRadicalRed": "Radical Redも試してね！",
  "eeveeExpo": "Eevee Expo!",
  "checkOutYnoproject": "YNOprojectをチェックしてね！",
  "breedersInSpace": "ブリーダー宇宙人？",
  "alsoTryPokemonUnbound": "Pokemon Unboundも試してね！",
  "tryTheJohtoDragonChallenge": "ジョウトドラゴンチャレンジしてみて！",
  "basicReadingAbilityRecommended": "基本的な読解力が推奨される！",
  "shoutoutsToTheArtists": "アーティストに大感謝！",
  "gamblingNotEncouraged": "ギャンブルはおすすめしません！",
  "dontForgetToTakeABreak": "たまには休憩を取りましょう！",
  "wEvent": "ネ申イベント！",
  "ifItsNotAccurateItsAccurate": "命中度をあげなくちゃ！",
  "everyLossIsProgressMade": "七転び八起き　ザ・ゲーム！",
  "itsAFeatureNotABug": "バグじゃなくて特色です！",
  "theEggsAreNotForEating": "タマゴを召し上がることはご遠慮ください！",
  "7.8outOf10TooManyWaterBiomes": "7.8／10　水のバイオームありすぎ",
  "butNothingHappened": "しかし何も起こらない！",
  "thePowerOfScienceIsAmazing": "科学の力ってすげー！",
  "freeToPlay": "全然無料！",
  "theresATimeAndPlaceForEverything": "こういうものには使いどきがあるんだ！",
  "nowWithShinierShinies": "色とりどりな色違い！",
  "smilesGoForMiles": "みんあえがおであかるいギルド！",
  "haveANiceDay": "今日はハバナイスデーイ！",
  "redacted": "【諸略】",
  "hi": "ょ",
  "shinyOddsHigherThanYouThink": "意外と高い色違い遭遇の確率！",
  "notForProfit": "非営利！",
  "timeForYourDailyRun": "デイリーランの時間だ！",
  "moreEggsThanADaycare": "育て屋よりタマゴが多い！",
  "disclaimerHarshSunDoesNotGiveVitaminD": "免責：ひでりがビタミンＤの供給源ではありません！",
  "whoNeedsAMap": "地図に書いてあるはずのシティが見当たらない！",
  "luxrayIsNotADarkType": "レントラーがあくタイプじゃない！",
  "selfDestructiveEncounters": "自爆の遭遇！",
  "pokerogueMorse": ".--. --- -.- . .-. --- --. ..- .",
  "smiley": "・ω・",
  "beAwareOfPassives": "パッシブを気づいてください！",
  "vaultinVeluzas": "へいらっしゃい！",
  "tooManyStarters": "スターターがいっぱい！",
  "checkTheWiki": "Pokérogue Wikiを利用してね！",
  "winWithYourFavorites": "好きなポケモンで勝てる！",
  "alsoTryPokerogueWait": "PokéRogueも試してね！　あ　ちょっ",
  "tryOutHoneyGather": "みつあつめを利用して！",
  "p": "（Ｐ）",
  "flipYourDeviceToEvolveInkay": "マーイーカを進化にはデバイスを逆さまにして！",
  "inArceusWeTrust": "イン・ アレセウス・ウィー・トラスト",
  "whyDidTheTorchicCrossTheRoad": "どうして、アチャモは道を横切ったの？",
  "goodLuck": "頑張ってね！",
  "fuseWisely": "計画的に吸収合体してね！",
  "prepareForTroubleAndMakeItDouble": "なんだかんだと聞かれたら答えてあげるのが世の情け！",
  "regirock": "ÜN ÜN ÜN",
  "checkTheSubreddit": "Pokérogue Subrebbitもチェックしてね！",
  "betterNerfGreninja": "ゲッコウガをナーフかも！",
  "inCaseOfUpdateClearYourCache": "アップデートのときにはキャッシュを削除！",
  "iLikeMyEggsVouchered": "焼き立てタマゴってあるわけない！",
  "YOU": "オマエ！",
  "noAddedSugar": "ノンシュガー！",
  "notSponsored": "このゲームこは、スポンサーの提供でお送りしません！",
  "saltCured": "しおづけた！",
  "pixelPerfection": "パーフェクトピクセルズ！",
  "dontForgetYourPassword": "パスワードを忘れずに！",
  "clownEncounters": "クラウンを遭遇！",
  "fullOfBerries": "きのみ溢れてる！",
  "mew": "ミュウはトラックの下にいません！",
  "makeItRainAndYourProblemsGoAway": "ゴールドラッシュで問題が溶ける！",
  "number591IsLookingOff": "＃５９１の見た目はちょっと……",
  "halloween": {
    "gourgeistUsedTrickOrTreat": "パンプジンの　ハロウィン！",
    "letsSnuggleForever": "ぽかぼかフレンドタイム！"
  },
  "xmas": {
    "diamondsFromTheSky": "宝石箱みたい散りばめたTWINKLE SNOW！"
  },
  "newYears": {
    "happyNewYear": "あけましておめでとうございます！"
  }
}
