{
  "sendOut": "Отправить",
  "summary": "Сводка",
  "pokedex": "Покедекс",
  "cancel": "Отмена",
  "release": "Отпустить",
  "apply": "Применить",
  "teach": "Научить",
  "splice": "Срастить",
  "unsplice": "Разъединить",
  "activate": "Включить",
  "deactivate": "Выключить",
  "transfer": "Перенести",
  "all": "Всё",
  "passBaton": "Передать эстафету",
  "unpauseEvolution": "Возобн. эволюцию",
  "pauseEvolution": "Приост. эволюцию",
  "revive": "Оживить",
  "rename": "Переименовать",
  "select": "Выбрать",
  "choosePokemon": "Выберите Покемона.",
  "doWhatWithThisPokemon": "Что сделать с этим Покемоном?",
  "noEnergy": "У {{pokemonName}} не осталось\nэнергии для битвы!",
  "hasEnergy": "У {{pokemonName}} ещё есть\n энергия для битвы!",
  "cantBeUsed": "{{pokemonName}} не подходит\nдля этого испытания!",
  "tooManyItems": "{{pokemonName}} не может взять\nбольше этого предмета!",
  "anyEffect": "Это не окажет никакого эффекта.",
  "unpausedEvolutions": "Эволюции для {{pokemonName}} возобновлены.",
  "pausedEvolutions": "Эволюции для {{pokemonName}} приостановлены.",
  "unspliceConfirmation": "Вы действительно хотите разъединить {{fusionName}}\nс {{pokemonName}}? {{fusionName}} будет потерян.",
  "wasReverted": "{{fusionName}} был возвращен к {{pokemonName}}.",
  "releaseConfirmation": "Вы точно хотите отпустить {{pokemonName}}?",
  "releaseInBattle": "Нельзя отпустить Покемона в бою!",
  "selectAMove": "Выберите приём.",
  "changeQuantity": "Выберите удерживаемый предмет для передачи.\nИспользуйте < и >, чтобы изменить количество.",
  "selectAnotherPokemonToSplice": "Выберите другого Покемона для сращивания.",
  "fusionForbidden": "Эти Покемоны не могут быть сращенны вместе!",
  "cancelButton": "Отмена",
  "able": "Может",
  "notAble": "Не может",
  "learned": "Выучено",
  "goodbye": "Прощай, {{pokemonName}}!",
  "byebye": "Пока-пока, {{pokemonName}}!",
  "farewell": "Прощай навек, {{pokemonName}}!",
  "soLong": "До скорого, {{pokemonName}}!",
  "thisIsWhereWePart": "На этом наши пути расходятся, {{pokemonName}}!",
  "illMissYou": "Буду скучать, {{pokemonName}}!",
  "illNeverForgetYou": "Ты навсегда в моём сердце, {{pokemonName}}!",
  "untilWeMeetAgain": "До новой встречи, {{pokemonName}}!",
  "sayonara": "Саёнара, {{pokemonName}}!",
  "smellYaLater": "Ну, бывай, {{pokemonName}}!"
}
